<?xml version="1.0" encoding="utf-8"?><ADDRESSOBJECTS><OBJECT ID="1148911" OBJECTID="923759" OBJECTGUID="c6883722-7941-420a-b0a9-d1092495c6bd" CHANGEID="2552671" NAME="СОТ Ручеёк" TYPENAME="тер." LEVEL="7" OPERTYPEID="10" PREVID="0" NEXTID="52126512" UPDATEDATE="2024-09-11" STARTDATE="2017-10-02" ENDDATE="2024-09-11" ISACTUAL="0" ISACTIVE="0" /><OBJECT ID="52126016" OBJECTID="165125667" OBJECTGUID="a4d65363-bbc8-47d2-bdb0-c9833fa572df" CHANGEID="600751103" NAME="Сказочный" TYPENAME="пер." LEVEL="8" OPERTYPEID="10" PREVID="0" NEXTID="0" UPDATEDATE="2024-09-09" STARTDATE="2024-09-09" ENDDATE="2079-06-06" ISACTUAL="1" ISACTIVE="1" /><OBJECT ID="52126368" OBJECTID="165180603" OBJECTGUID="e0053066-aebc-4af6-882e-19880781e5e0" CHANGEID="600843502" NAME="автодорога Москва-Санкт-Петербург" TYPENAME="тер." LEVEL="7" OPERTYPEID="10" PREVID="0" NEXTID="0" UPDATEDATE="2024-09-10" STARTDATE="2024-09-10" ENDDATE="2079-06-06" ISACTUAL="1" ISACTIVE="1" /><OBJECT ID="52126437" OBJECTID="165200198" OBJECTGUID="455c8952-08cb-46bf-94fe-6401030ec611" CHANGEID="600897261" NAME="501-й" TYPENAME="км" LEVEL="8" OPERTYPEID="10" PREVID="0" NEXTID="0" UPDATEDATE="2024-09-11" STARTDATE="2024-09-11" ENDDATE="2079-06-06" ISACTUAL="1" ISACTIVE="1" /><OBJECT ID="52126512" OBJECTID="923759" OBJECTGUID="c6883722-7941-420a-b0a9-d1092495c6bd" CHANGEID="600924958" NAME="СОТ Ручеёк" TYPENAME="тер." LEVEL="7" OPERTYPEID="30" PREVID="1148911" NEXTID="0" UPDATEDATE="2024-09-11" STARTDATE="2024-09-11" ENDDATE="2079-06-06" ISACTUAL="1" ISACTIVE="0" /><OBJECT ID="1155949" OBJECTID="929532" OBJECTGUID="f12032d7-a89d-4441-895d-9e728ca08d87" CHANGEID="2566830" NAME="Заречье (Новорахинское с/п)" TYPENAME="д" LEVEL="6" OPERTYPEID="1" PREVID="0" NEXTID="52126641" UPDATEDATE="2024-09-12" STARTDATE="1900-01-01" ENDDATE="2024-09-12" ISACTUAL="0" ISACTIVE="0" /><OBJECT ID="52126641" OBJECTID="929532" OBJECTGUID="f12032d7-a89d-4441-895d-9e728ca08d87" CHANGEID="600957977" NAME="Заречье" TYPENAME="д" LEVEL="6" OPERTYPEID="20" PREVID="1155949" UPDATEDATE="2024-09-12" STARTDATE="2024-09-12" ENDDATE="2079-06-06" ISACTUAL="1" ISACTIVE="1" /><OBJECT ID="1149573" OBJECTID="924312" OBJECTGUID="b16fe377-3841-4c9b-b6ef-4cc82a4c59a8" CHANGEID="2554159" NAME="Озерки (Новорахинское с/п)" TYPENAME="д" LEVEL="6" OPERTYPEID="1" PREVID="0" NEXTID="52126642" UPDATEDATE="2024-09-12" STARTDATE="1900-01-01" ENDDATE="2024-09-12" ISACTUAL="0" ISACTIVE="0" /><OBJECT ID="52126642" OBJECTID="924312" OBJECTGUID="b16fe377-3841-4c9b-b6ef-4cc82a4c59a8" CHANGEID="600957997" NAME="Озерки" TYPENAME="д" LEVEL="6" OPERTYPEID="20" PREVID="1149573" UPDATEDATE="2024-09-12" STARTDATE="2024-09-12" ENDDATE="2079-06-06" ISACTUAL="1" ISACTIVE="1" /></ADDRESSOBJECTS>