<?xml version="1.0" encoding="utf-8"?><REESTR_OBJECTS><OBJECT OBJECTID="49902216" OBJECTGUID="d68b60bf-af17-4548-956e-6b6511cc6659" CHANGEID="600881661" ISACTIVE="1" LEVELID="10" CREATEDATE="2017-10-06" UPDATEDATE="2024-09-11" /><OBJECT OBJECTID="83371364" OBJECTGUID="aac9c7d1-91f3-4a4d-ae60-ae77000831dc" CHANGEID="600883807" ISACTIVE="0" LEVELID="10" CREATEDATE="2017-10-06" UPDATEDATE="2024-09-11" /><OBJECT OBJECTID="4323256" OBJECTGUID="5d324f7d-72b1-42fc-b9d5-959df8991eac" CHANGEID="600784751" ISACTIVE="1" LEVELID="10" CREATEDATE="2017-12-18" UPDATEDATE="2024-09-09" /><OBJECT OBJECTID="83592544" OBJECTGUID="bb9188c0-db6e-4914-9590-e7efb5baba10" CHANGEID="600917361" ISACTIVE="1" LEVELID="10" CREATEDATE="2017-12-18" UPDATEDATE="2024-09-11" /><OBJECT OBJECTID="57166935" OBJECTGUID="689aa3ef-5768-442f-9ddf-01f402818c1d" CHANGEID="600874200" ISACTIVE="0" LEVELID="10" CREATEDATE="2017-10-06" UPDATEDATE="2024-09-11" /><OBJECT OBJECTID="8575959" OBJECTGUID="ecc573e8-e8d9-4918-9906-cc6700d730f5" CHANGEID="600886631" ISACTIVE="1" LEVELID="10" CREATEDATE="2017-10-06" UPDATEDATE="2024-09-11" /><OBJECT OBJECTID="58917841" OBJECTGUID="350e038f-e68c-4f65-a910-dfce8663d8fb" CHANGEID="600935330" ISACTIVE="1" LEVELID="10" CREATEDATE="2017-12-18" UPDATEDATE="2024-09-12" /><OBJECT OBJECTID="24921748" OBJECTGUID="7336eb4f-033a-4f7f-bb43-202f90b7cea6" CHANGEID="600881656" ISACTIVE="0" LEVELID="10" CREATEDATE="2017-10-06" UPDATEDATE="2024-09-11" /><OBJECT OBJECTID="57982743" OBJECTGUID="8e29ede2-0199-451e-adf9-a5d78db8b82f" CHANGEID="600936773" ISACTIVE="0" LEVELID="10" CREATEDATE="2017-10-06" UPDATEDATE="2024-09-12" /><OBJECT OBJECTID="8377010" OBJECTGUID="ed632c3b-36c1-4b76-9a04-3ca40d1e183f" CHANGEID="600881664" ISACTIVE="1" LEVELID="10" CREATEDATE="2019-06-07" UPDATEDATE="2024-09-11" /><OBJECT OBJECTID="82486618" OBJECTGUID="713f0b3d-6935-47a7-8378-cc8c91bfcac2" CHANGEID="600807688" ISACTIVE="1" LEVELID="10" CREATEDATE="2016-06-21" UPDATEDATE="2024-09-10" /><OBJECT OBJECTID="71911079" OBJECTGUID="1101d3f3-c842-41ff-ba1a-533bba4694f4" CHANGEID="600807692" ISACTIVE="1" LEVELID="10" CREATEDATE="2017-12-18" UPDATEDATE="2024-09-10" /><OBJECT OBJECTID="54877530" OBJECTGUID="10facf43-a53d-4d39-b556-5dc91aa1d95f" CHANGEID="600880444" ISACTIVE="0" LEVELID="10" CREATEDATE="2017-10-06" UPDATEDATE="2024-09-11" /><OBJECT OBJECTID="28980572" OBJECTGUID="7aba041a-0fe2-4f6d-9944-253ad60a8b12" CHANGEID="600880432" ISACTIVE="0" LEVELID="10" CREATEDATE="2019-01-24" UPDATEDATE="2024-09-11" /><OBJECT OBJECTID="163088851" OBJECTGUID="45cfc790-6193-4a66-a83d-8b4d426f8aba" CHANGEID="600889842" ISACTIVE="1" LEVELID="10" CREATEDATE="2024-04-05" UPDATEDATE="2024-09-11" /><OBJECT OBJECTID="9983851" OBJECTGUID="49fff3bf-8658-446b-8ff1-45cc3659e0cd" CHANGEID="600904540" ISACTIVE="1" LEVELID="10" CREATEDATE="2015-11-27" UPDATEDATE="2024-09-11" /><OBJECT OBJECTID="36304968" OBJECTGUID="881f5904-b891-4bee-9c43-17a3a2477389" CHANGEID="600936765" ISACTIVE="0" LEVELID="10" CREATEDATE="2017-10-06" UPDATEDATE="2024-09-12" /><OBJECT OBJECTID="71644877" OBJECTGUID="00091198-e632-4f49-9af1-082ce034c9b9" CHANGEID="600939716" ISACTIVE="1" LEVELID="10" CREATEDATE="2017-12-17" UPDATEDATE="2024-09-12" /><OBJECT OBJECTID="73200004" OBJECTGUID="57680926-4121-4a95-9cce-00200f40530c" CHANGEID="600947031" ISACTIVE="0" LEVELID="10" CREATEDATE="2017-12-17" UPDATEDATE="2024-09-12" /><OBJECT OBJECTID="26168243" OBJECTGUID="8f18d8f8-29b8-4abd-b153-dae450db070e" CHANGEID="600807693" ISACTIVE="1" LEVELID="10" CREATEDATE="2019-07-10" UPDATEDATE="2024-09-10" /><OBJECT OBJECTID="61712647" OBJECTGUID="89b60649-4d4d-4117-8548-1d766c350545" CHANGEID="600764756" ISACTIVE="1" LEVELID="10" CREATEDATE="2017-12-17" UPDATEDATE="2024-09-09" /><OBJECT OBJECTID="79783690" OBJECTGUID="811dcb03-1761-4549-9944-79047071a9d0" CHANGEID="600879144" ISACTIVE="0" LEVELID="10" CREATEDATE="2017-10-06" UPDATEDATE="2024-09-11" /><OBJECT OBJECTID="70603091" OBJECTGUID="3dab503a-a943-48bc-9894-47d0b93ea984" CHANGEID="600936768" ISACTIVE="0" LEVELID="10" CREATEDATE="2017-10-06" UPDATEDATE="2024-09-12" /><OBJECT OBJECTID="10899961" OBJECTGUID="8ab70688-a84c-43b3-99d4-1960969fee4a" CHANGEID="600899913" ISACTIVE="1" LEVELID="10" CREATEDATE="2012-01-10" UPDATEDATE="2024-09-11" /><OBJECT OBJECTID="58684364" OBJECTGUID="d53e6b13-9bc4-4689-a52b-056234e81076" CHANGEID="600812324" ISACTIVE="0" LEVELID="10" CREATEDATE="2015-09-02" UPDATEDATE="2024-09-10" /><OBJECT OBJECTID="55389734" OBJECTGUID="b076ec54-e9b5-48e0-bdcd-84aecdae4d91" CHANGEID="600819373" ISACTIVE="1" LEVELID="10" CREATEDATE="2015-09-24" UPDATEDATE="2024-09-10" /><OBJECT OBJECTID="49155037" OBJECTGUID="33f6edd9-94b5-49fc-ab18-9ea16253f255" CHANGEID="600935336" ISACTIVE="1" LEVELID="10" CREATEDATE="2017-10-06" UPDATEDATE="2024-09-12" /><OBJECT OBJECTID="79281676" OBJECTGUID="c4c26b7a-1ea3-41ed-88dc-0ee7a34271b8" CHANGEID="600906883" ISACTIVE="0" LEVELID="10" CREATEDATE="2017-12-17" UPDATEDATE="2024-09-11" /><OBJECT OBJECTID="14813735" OBJECTGUID="3aee4b6c-f066-42a0-990b-025c0c43e83f" CHANGEID="600776536" ISACTIVE="0" LEVELID="10" CREATEDATE="2017-12-17" UPDATEDATE="2024-09-09" /><OBJECT OBJECTID="8132325" OBJECTGUID="fd96adbc-9e72-4936-9b13-f26321d9258e" CHANGEID="600797431" ISACTIVE="1" LEVELID="10" CREATEDATE="2019-07-10" UPDATEDATE="2024-09-10" /><OBJECT OBJECTID="164265775" OBJECTGUID="25416211-b217-494c-acd5-f6c98dc5e499" CHANGEID="600859931" ISACTIVE="1" LEVELID="10" CREATEDATE="2024-07-16" UPDATEDATE="2024-09-11" /><OBJECT OBJECTID="164291082" OBJECTGUID="fc40e585-e45d-4bf1-9a4c-c2d5501d4260" CHANGEID="600939824" ISACTIVE="1" LEVELID="10" CREATEDATE="2024-07-17" UPDATEDATE="2024-09-12" /><OBJECT OBJECTID="164291081" OBJECTGUID="ca355dab-5967-424d-ac17-118fb9747192" CHANGEID="600939825" ISACTIVE="1" LEVELID="10" CREATEDATE="2024-07-17" UPDATEDATE="2024-09-12" /><OBJECT OBJECTID="164291083" OBJECTGUID="03da3eba-35a4-4687-81ca-21fc94ea4951" CHANGEID="600939826" ISACTIVE="1" LEVELID="10" CREATEDATE="2024-07-17" UPDATEDATE="2024-09-12" /><OBJECT OBJECTID="164291080" OBJECTGUID="e95462c4-4136-4b16-8937-0ea4a330fa2f" CHANGEID="600939827" ISACTIVE="1" LEVELID="10" CREATEDATE="2024-07-17" UPDATEDATE="2024-09-12" /><OBJECT OBJECTID="164291079" OBJECTGUID="1edebbc8-1266-4f0e-b49d-d00b207cf6d8" CHANGEID="600939828" ISACTIVE="1" LEVELID="10" CREATEDATE="2024-07-17" UPDATEDATE="2024-09-12" /><OBJECT OBJECTID="164291078" OBJECTGUID="e637a6af-31aa-4f41-aff5-58d4cd4b87ee" CHANGEID="600939829" ISACTIVE="1" LEVELID="10" CREATEDATE="2024-07-17" UPDATEDATE="2024-09-12" /><OBJECT OBJECTID="164291077" OBJECTGUID="85de81b5-0495-4ed2-8e10-be0d6161a360" CHANGEID="600939830" ISACTIVE="1" LEVELID="10" CREATEDATE="2024-07-17" UPDATEDATE="2024-09-12" /><OBJECT OBJECTID="164291076" OBJECTGUID="865f1db4-eef3-48ba-b98d-01c1d372d516" CHANGEID="600939831" ISACTIVE="1" LEVELID="10" CREATEDATE="2024-07-17" UPDATEDATE="2024-09-12" /><OBJECT OBJECTID="164310380" OBJECTGUID="f14dfb10-b056-4f86-880a-81828a31f358" CHANGEID="600859929" ISACTIVE="1" LEVELID="10" CREATEDATE="2024-07-18" UPDATEDATE="2024-09-11" /><OBJECT OBJECTID="164935584" OBJECTGUID="ec99f240-77e8-40d4-9621-99ebd0e1774f" CHANGEID="600860095" ISACTIVE="1" LEVELID="10" CREATEDATE="2024-08-29" UPDATEDATE="2024-09-11" /><OBJECT OBJECTID="164923886" OBJECTGUID="c0fccb1b-f71f-4e18-aa54-bd2dc5e164ea" CHANGEID="600860097" ISACTIVE="1" LEVELID="10" CREATEDATE="2024-08-28" UPDATEDATE="2024-09-11" /><OBJECT OBJECTID="165117092" OBJECTGUID="ed5e9f7b-4f0d-44e9-a6d1-0317734ffd59" CHANGEID="600738040" ISACTIVE="1" LEVELID="10" CREATEDATE="2024-09-09" UPDATEDATE="2024-09-09" /><OBJECT OBJECTID="56602555" OBJECTGUID="280a5806-6770-45b7-aca1-db4e60426d38" CHANGEID="600738547" ISACTIVE="1" LEVELID="11" CREATEDATE="2017-04-11" UPDATEDATE="2024-09-09" /><OBJECT OBJECTID="165117333" OBJECTGUID="6f2d2b47-81c2-4638-913b-dda57ad7043c" CHANGEID="600738549" ISACTIVE="1" LEVELID="9" CREATEDATE="2024-09-09" UPDATEDATE="2024-09-09" /><OBJECT OBJECTID="165117334" OBJECTGUID="a15b8144-86c9-422d-b847-6c33dfa4a3ba" CHANGEID="600738550" ISACTIVE="1" LEVELID="9" CREATEDATE="2024-09-09" UPDATEDATE="2024-09-09" /><OBJECT OBJECTID="165117361" OBJECTGUID="b774e6c3-7d08-40f6-a3c0-174348147e28" CHANGEID="600738577" ISACTIVE="1" LEVELID="10" CREATEDATE="2024-09-09" UPDATEDATE="2024-09-09" /><OBJECT OBJECTID="165117362" OBJECTGUID="2def3adc-16f3-42e0-b3d8-d2b839e127e0" CHANGEID="600738578" ISACTIVE="1" LEVELID="10" CREATEDATE="2024-09-09" UPDATEDATE="2024-09-09" /><OBJECT OBJECTID="78675738" OBJECTGUID="bce4d017-49cf-4763-ae6c-5396f54bc702" CHANGEID="600738597" ISACTIVE="0" LEVELID="11" CREATEDATE="2019-04-12" UPDATEDATE="2024-09-09" /><OBJECT OBJECTID="165117332" OBJECTGUID="cf84527a-b7f3-4488-b75c-68477e2c4593" CHANGEID="600738548" ISACTIVE="1" LEVELID="9" CREATEDATE="2024-09-09" UPDATEDATE="2024-09-09" /><OBJECT OBJECTID="165117335" OBJECTGUID="a8d5f30a-9852-4100-b4d9-07903bcabb97" CHANGEID="600738551" ISACTIVE="1" LEVELID="9" CREATEDATE="2024-09-09" UPDATEDATE="2024-09-09" /><OBJECT OBJECTID="165117336" OBJECTGUID="f55500c3-28f3-41a7-b2cf-d377b541f134" CHANGEID="600738552" ISACTIVE="1" LEVELID="9" CREATEDATE="2024-09-09" UPDATEDATE="2024-09-09" /><OBJECT OBJECTID="165117337" OBJECTGUID="946cb300-3a39-4f6d-a063-2073b6260c09" CHANGEID="600738553" ISACTIVE="1" LEVELID="9" CREATEDATE="2024-09-09" UPDATEDATE="2024-09-09" /><OBJECT OBJECTID="165117338" OBJECTGUID="c6abbc7c-fc02-4e30-b88c-70331282c2fd" CHANGEID="600738554" ISACTIVE="1" LEVELID="9" CREATEDATE="2024-09-09" UPDATEDATE="2024-09-09" /><OBJECT OBJECTID="165117339" OBJECTGUID="137e147e-a0ce-442a-9617-a8d0b3ee9f9f" CHANGEID="600738555" ISACTIVE="1" LEVELID="9" CREATEDATE="2024-09-09" UPDATEDATE="2024-09-09" /><OBJECT OBJECTID="165117340" OBJECTGUID="562cd119-2ba3-4c8c-8db9-7400a86b3d25" CHANGEID="600738556" ISACTIVE="1" LEVELID="9" CREATEDATE="2024-09-09" UPDATEDATE="2024-09-09" /><OBJECT OBJECTID="165117341" OBJECTGUID="6009417d-6760-455c-9e7f-1ebb52a13c89" CHANGEID="600738557" ISACTIVE="1" LEVELID="9" CREATEDATE="2024-09-09" UPDATEDATE="2024-09-09" /><OBJECT OBJECTID="165117342" OBJECTGUID="f2766953-ef08-430c-8f5e-1df393fafbae" CHANGEID="600738558" ISACTIVE="1" LEVELID="9" CREATEDATE="2024-09-09" UPDATEDATE="2024-09-09" /><OBJECT OBJECTID="165117343" OBJECTGUID="be2d1e59-00d3-4ffc-9ce9-42ba5c985da5" CHANGEID="600738559" ISACTIVE="1" LEVELID="9" CREATEDATE="2024-09-09" UPDATEDATE="2024-09-09" /><OBJECT OBJECTID="165117344" OBJECTGUID="e001a1f2-e75a-4189-924c-a73ae3ab5717" CHANGEID="600738560" ISACTIVE="1" LEVELID="9" CREATEDATE="2024-09-09" UPDATEDATE="2024-09-09" /><OBJECT OBJECTID="165117345" OBJECTGUID="f20542ff-a888-4a5f-983c-44b6bc058559" CHANGEID="600738561" ISACTIVE="1" LEVELID="9" CREATEDATE="2024-09-09" UPDATEDATE="2024-09-09" /><OBJECT OBJECTID="165117346" OBJECTGUID="acb818e8-6c73-4e11-a209-6f449ce84e5e" CHANGEID="600738562" ISACTIVE="1" LEVELID="9" CREATEDATE="2024-09-09" UPDATEDATE="2024-09-09" /><OBJECT OBJECTID="165117347" OBJECTGUID="93dcf257-5ac2-4352-bb5e-bd3d105ad1e9" CHANGEID="600738563" ISACTIVE="1" LEVELID="9" CREATEDATE="2024-09-09" UPDATEDATE="2024-09-09" /><OBJECT OBJECTID="165117348" OBJECTGUID="d53aebc7-d571-4c1d-9902-5b2123495a16" CHANGEID="600738564" ISACTIVE="1" LEVELID="9" CREATEDATE="2024-09-09" UPDATEDATE="2024-09-09" /><OBJECT OBJECTID="165117349" OBJECTGUID="2327c83b-3c8b-4d4e-ae0e-60b580ea529b" CHANGEID="600738565" ISACTIVE="1" LEVELID="9" CREATEDATE="2024-09-09" UPDATEDATE="2024-09-09" /><OBJECT OBJECTID="165117350" OBJECTGUID="74230c83-8efe-499a-8a48-374d280e7eb5" CHANGEID="600738566" ISACTIVE="1" LEVELID="9" CREATEDATE="2024-09-09" UPDATEDATE="2024-09-09" /><OBJECT OBJECTID="165117351" OBJECTGUID="c4f5fd98-1562-42ba-bcf0-afe3f37a62a4" CHANGEID="600738567" ISACTIVE="1" LEVELID="9" CREATEDATE="2024-09-09" UPDATEDATE="2024-09-09" /><OBJECT OBJECTID="165117352" OBJECTGUID="9b71c6e3-23d0-42c4-9305-e398f2d82b12" CHANGEID="600738568" ISACTIVE="1" LEVELID="9" CREATEDATE="2024-09-09" UPDATEDATE="2024-09-09" /><OBJECT OBJECTID="165117353" OBJECTGUID="c69af0f9-d52e-4083-9002-fed046e24f24" CHANGEID="600738569" ISACTIVE="1" LEVELID="9" CREATEDATE="2024-09-09" UPDATEDATE="2024-09-09" /><OBJECT OBJECTID="165117354" OBJECTGUID="cd5ac044-bf2e-475e-9d87-256c82cd8851" CHANGEID="600738570" ISACTIVE="1" LEVELID="9" CREATEDATE="2024-09-09" UPDATEDATE="2024-09-09" /><OBJECT OBJECTID="165117355" OBJECTGUID="25bff025-e93e-42b2-96f3-cf73d411686b" CHANGEID="600738571" ISACTIVE="1" LEVELID="9" CREATEDATE="2024-09-09" UPDATEDATE="2024-09-09" /><OBJECT OBJECTID="165117356" OBJECTGUID="65001598-23d2-4e6f-9038-b99176332d16" CHANGEID="600738572" ISACTIVE="1" LEVELID="9" CREATEDATE="2024-09-09" UPDATEDATE="2024-09-09" /><OBJECT OBJECTID="165117357" OBJECTGUID="6d6e4946-f282-4466-8a1c-ecc6030c443c" CHANGEID="600738573" ISACTIVE="1" LEVELID="9" CREATEDATE="2024-09-09" UPDATEDATE="2024-09-09" /><OBJECT OBJECTID="165117358" OBJECTGUID="ebf95ad7-80e6-41ea-b85a-65efa4834b2c" CHANGEID="600738574" ISACTIVE="1" LEVELID="9" CREATEDATE="2024-09-09" UPDATEDATE="2024-09-09" /><OBJECT OBJECTID="165117359" OBJECTGUID="ae70ddbe-7536-49d9-bf4a-4c8bbb72ddbd" CHANGEID="600738575" ISACTIVE="1" LEVELID="9" CREATEDATE="2024-09-09" UPDATEDATE="2024-09-09" /><OBJECT OBJECTID="165117360" OBJECTGUID="11ea8922-f88e-4f94-87fb-9f9fe7dfcb81" CHANGEID="600738576" ISACTIVE="1" LEVELID="9" CREATEDATE="2024-09-09" UPDATEDATE="2024-09-09" /><OBJECT OBJECTID="165117363" OBJECTGUID="2793a4ff-1713-408c-a418-91474a298a85" CHANGEID="600738579" ISACTIVE="1" LEVELID="10" CREATEDATE="2024-09-09" UPDATEDATE="2024-09-09" /><OBJECT OBJECTID="78675377" OBJECTGUID="a7cf9cfd-f7c0-459e-af7f-a3cb1177c0b6" CHANGEID="600738596" ISACTIVE="0" LEVELID="11" CREATEDATE="2019-07-19" UPDATEDATE="2024-09-09" /><OBJECT OBJECTID="165117692" OBJECTGUID="576d5c7a-c18a-4c97-a873-1a2f8151dec6" CHANGEID="600739202" ISACTIVE="1" LEVELID="9" CREATEDATE="2024-09-09" UPDATEDATE="2024-09-09" /><OBJECT OBJECTID="165117891" OBJECTGUID="f35bee72-ba3b-4a29-a2b6-5f301aff2ef8" CHANGEID="600739445" ISACTIVE="1" LEVELID="10" CREATEDATE="2024-09-09" UPDATEDATE="2024-09-09" /><OBJECT OBJECTID="165117890" OBJECTGUID="33a2de57-84d0-4090-b9cd-54815b81cc35" CHANGEID="600739444" ISACTIVE="1" LEVELID="10" CREATEDATE="2024-09-09" UPDATEDATE="2024-09-09" /><OBJECT OBJECTID="165117892" OBJECTGUID="7b6e6d10-9ed6-431d-93f0-3ed380c04c9f" CHANGEID="600739446" ISACTIVE="1" LEVELID="10" CREATEDATE="2024-09-09" UPDATEDATE="2024-09-09" /><OBJECT OBJECTID="165118273" OBJECTGUID="86071c20-5455-48d8-84ea-def594d03395" CHANGEID="600740036" ISACTIVE="1" LEVELID="9" CREATEDATE="2024-09-09" UPDATEDATE="2024-09-09" /><OBJECT OBJECTID="165118844" OBJECTGUID="a9bfc75c-ffab-411a-b0ba-4f32db7e74c6" CHANGEID="600740846" ISACTIVE="1" LEVELID="9" CREATEDATE="2024-09-09" UPDATEDATE="2024-09-09" /><OBJECT OBJECTID="165118845" OBJECTGUID="0cfaab90-8501-40c6-b43a-c52e5ffc40ed" CHANGEID="600740847" ISACTIVE="1" LEVELID="9" CREATEDATE="2024-09-09" UPDATEDATE="2024-09-09" /><OBJECT OBJECTID="165118835" OBJECTGUID="cd7e4b4e-eee3-417e-9f9a-9e4f1890783d" CHANGEID="600740837" ISACTIVE="1" LEVELID="9" CREATEDATE="2024-09-09" UPDATEDATE="2024-09-09" /><OBJECT OBJECTID="165118842" OBJECTGUID="ab7650bc-3396-44cd-a8dc-019c2cb6ffdc" CHANGEID="600740844" ISACTIVE="1" LEVELID="9" CREATEDATE="2024-09-09" UPDATEDATE="2024-09-09" /><OBJECT OBJECTID="165118843" OBJECTGUID="ed3cb20b-79d0-465a-b9e2-b56d216763b2" CHANGEID="600740845" ISACTIVE="1" LEVELID="9" CREATEDATE="2024-09-09" UPDATEDATE="2024-09-09" /><OBJECT OBJECTID="165119728" OBJECTGUID="083524ed-d176-4863-a281-229516d98ff9" CHANGEID="600742174" ISACTIVE="1" LEVELID="9" CREATEDATE="2024-09-09" UPDATEDATE="2024-09-09" /><OBJECT OBJECTID="76324567" OBJECTGUID="c3b992fd-fe37-4073-a517-41d16fc611a3" CHANGEID="600743009" ISACTIVE="0" LEVELID="11" CREATEDATE="2018-08-28" UPDATEDATE="2024-09-09" /><OBJECT OBJECTID="76324554" OBJECTGUID="b4a7d947-3c9c-4ae5-aadd-97cb0fc80712" CHANGEID="600743011" ISACTIVE="0" LEVELID="11" CREATEDATE="2018-08-28" UPDATEDATE="2024-09-09" /><OBJECT OBJECTID="165120339" OBJECTGUID="1c245c9f-ae71-4a06-be6a-89de224e4ce8" CHANGEID="600743064" ISACTIVE="1" LEVELID="9" CREATEDATE="2024-09-09" UPDATEDATE="2024-09-09" /><OBJECT OBJECTID="165120334" OBJECTGUID="7dcaa1c9-236c-4459-9764-8490880ac24c" CHANGEID="600743057" ISACTIVE="1" LEVELID="9" CREATEDATE="2024-09-09" UPDATEDATE="2024-09-09" /><OBJECT OBJECTID="89912370" OBJECTGUID="a129a0fa-8b6d-4d9e-bacc-4776393e34f8" CHANGEID="600743453" ISACTIVE="0" LEVELID="9" CREATEDATE="2019-04-23" UPDATEDATE="2024-09-09" /><OBJECT OBJECTID="165160761" OBJECTGUID="f96c0302-ea74-4ef5-ba68-5cb6d33f49b4" CHANGEID="600812313" ISACTIVE="1" LEVELID="10" CREATEDATE="2024-09-10" UPDATEDATE="2024-09-10" /><OBJECT OBJECTID="60415376" OBJECTGUID="f2783af7-6bff-4778-903b-2aafc609eba1" CHANGEID="600812315" ISACTIVE="1" LEVELID="10" CREATEDATE="2012-02-08" UPDATEDATE="2024-09-10" /><OBJECT OBJECTID="161819613" OBJECTGUID="9deca4c0-cd1a-44b4-9e23-14afdbc60f79" CHANGEID="600812317" ISACTIVE="0" LEVELID="9" CREATEDATE="2023-12-19" UPDATEDATE="2024-09-10" /><OBJECT OBJECTID="159151452" OBJECTGUID="4f0aa58e-2cad-4dde-a82a-1cebdb3fab73" CHANGEID="600812319" ISACTIVE="0" LEVELID="9" CREATEDATE="2023-06-16" UPDATEDATE="2024-09-10" /><OBJECT OBJECTID="165160764" OBJECTGUID="b68f0a87-d0c9-40c8-9368-46a0e7131c6c" CHANGEID="600812321" ISACTIVE="1" LEVELID="11" CREATEDATE="2024-09-10" UPDATEDATE="2024-09-10" /><OBJECT OBJECTID="165160765" OBJECTGUID="7dc16e52-1393-471b-9074-593dddd050b6" CHANGEID="600812322" ISACTIVE="1" LEVELID="11" CREATEDATE="2024-09-10" UPDATEDATE="2024-09-10" /><OBJECT OBJECTID="159615859" OBJECTGUID="317e5e77-84d7-444e-95fa-2bd74096e665" CHANGEID="600743454" ISACTIVE="0" LEVELID="9" CREATEDATE="2023-08-08" UPDATEDATE="2024-09-09" /><OBJECT OBJECTID="165160762" OBJECTGUID="c0477367-1e79-4ff0-a367-804e0f490d8f" CHANGEID="600812316" ISACTIVE="1" LEVELID="8" CREATEDATE="2024-09-10" UPDATEDATE="2024-09-10" /><OBJECT OBJECTID="161819625" OBJECTGUID="d9c07316-6fb7-47af-80d3-cdddd8c45383" CHANGEID="600812318" ISACTIVE="0" LEVELID="9" CREATEDATE="2023-12-19" UPDATEDATE="2024-09-10" /><OBJECT OBJECTID="165160763" OBJECTGUID="1ba7ec41-69b9-4380-879f-57ce03181858" CHANGEID="600812320" ISACTIVE="1" LEVELID="11" CREATEDATE="2024-09-10" UPDATEDATE="2024-09-10" /><OBJECT OBJECTID="165120742" OBJECTGUID="4ad4076d-60d1-420f-a6a0-73750cd49d73" CHANGEID="600744247" ISACTIVE="1" LEVELID="9" CREATEDATE="2024-09-09" UPDATEDATE="2024-09-09" /><OBJECT OBJECTID="165120744" OBJECTGUID="562e97b4-e410-4026-9547-70e8235b2bfd" CHANGEID="600744249" ISACTIVE="1" LEVELID="10" CREATEDATE="2024-09-09" UPDATEDATE="2024-09-09" /><OBJECT OBJECTID="165120754" OBJECTGUID="9f8f5199-949b-452f-a45d-f13a401815d0" CHANGEID="600744261" ISACTIVE="1" LEVELID="12" CREATEDATE="2024-09-09" UPDATEDATE="2024-09-09" /><OBJECT OBJECTID="165121035" OBJECTGUID="68c28a4b-bf0e-4c0c-bc1e-7982139f9a91" CHANGEID="600744642" ISACTIVE="1" LEVELID="10" CREATEDATE="2024-09-09" UPDATEDATE="2024-09-09" /><OBJECT OBJECTID="165121046" OBJECTGUID="2547c4c3-5a84-45e6-8a4b-fb768e4a7fac" CHANGEID="600744657" ISACTIVE="1" LEVELID="9" CREATEDATE="2024-09-09" UPDATEDATE="2024-09-09" /><OBJECT OBJECTID="165121051" OBJECTGUID="d4415bff-4cf4-421f-b486-3d655565f97f" CHANGEID="600744665" ISACTIVE="1" LEVELID="10" CREATEDATE="2024-09-09" UPDATEDATE="2024-09-09" /><OBJECT OBJECTID="165121062" OBJECTGUID="a486d2f2-0257-4380-af8c-0b89af886c24" CHANGEID="600744678" ISACTIVE="1" LEVELID="9" CREATEDATE="2024-09-09" UPDATEDATE="2024-09-09" /><OBJECT OBJECTID="165121074" OBJECTGUID="b39b9af0-5ea4-40c8-b12b-7c8721652dc9" CHANGEID="600744698" ISACTIVE="1" LEVELID="9" CREATEDATE="2024-09-09" UPDATEDATE="2024-09-09" /><OBJECT OBJECTID="165121054" OBJECTGUID="d3ab3a70-21a3-4c35-ab46-bb8819c6b725" CHANGEID="600744668" ISACTIVE="1" LEVELID="9" CREATEDATE="2024-09-09" UPDATEDATE="2024-09-09" /><OBJECT OBJECTID="165121059" OBJECTGUID="a576c1ce-d858-4a1b-974e-9303d0548db5" CHANGEID="600744675" ISACTIVE="1" LEVELID="10" CREATEDATE="2024-09-09" UPDATEDATE="2024-09-09" /><OBJECT OBJECTID="165121071" OBJECTGUID="81012fd4-128f-49c9-8f6d-1e65e73e5c68" CHANGEID="600744695" ISACTIVE="1" LEVELID="10" CREATEDATE="2024-09-09" UPDATEDATE="2024-09-09" /><OBJECT OBJECTID="165121978" OBJECTGUID="b76bfd25-7c1a-430c-b071-12de19a6150c" CHANGEID="600746069" ISACTIVE="1" LEVELID="10" CREATEDATE="2024-09-09" UPDATEDATE="2024-09-09" /><OBJECT OBJECTID="165121979" OBJECTGUID="8a65cbcc-6e7b-4034-8268-483a7e877959" CHANGEID="600746070" ISACTIVE="1" LEVELID="9" CREATEDATE="2024-09-09" UPDATEDATE="2024-09-09" /><OBJECT OBJECTID="165121980" OBJECTGUID="1b7d3e9e-da1a-46cb-a94c-b88684fd4669" CHANGEID="600746071" ISACTIVE="1" LEVELID="10" CREATEDATE="2024-09-09" UPDATEDATE="2024-09-09" /><OBJECT OBJECTID="165124714" OBJECTGUID="ec4e7868-f915-4c71-bbc5-c1af30c65c6d" CHANGEID="600749668" ISACTIVE="1" LEVELID="9" CREATEDATE="2024-09-09" UPDATEDATE="2024-09-09" /><OBJECT OBJECTID="165124712" OBJECTGUID="4a6ef480-a6ee-4964-bfc3-c5a842c12f37" CHANGEID="600749665" ISACTIVE="1" LEVELID="9" CREATEDATE="2024-09-09" UPDATEDATE="2024-09-09" /><OBJECT OBJECTID="165124713" OBJECTGUID="f13af792-26ee-4ee9-b7d7-6966b33e94a7" CHANGEID="600749667" ISACTIVE="1" LEVELID="9" CREATEDATE="2024-09-09" UPDATEDATE="2024-09-09" /><OBJECT OBJECTID="165124931" OBJECTGUID="40e034a1-53ff-45ff-954c-f12265fef881" CHANGEID="600749918" ISACTIVE="1" LEVELID="9" CREATEDATE="2024-09-09" UPDATEDATE="2024-09-09" /><OBJECT OBJECTID="165126178" OBJECTGUID="beabb9a6-8b4a-4662-8885-3ffadd91053a" CHANGEID="600751849" ISACTIVE="1" LEVELID="9" CREATEDATE="2024-09-09" UPDATEDATE="2024-09-09" /><OBJECT OBJECTID="165126180" OBJECTGUID="c508e62e-ef5f-4a1b-b09d-470693dd6904" CHANGEID="600751851" ISACTIVE="1" LEVELID="9" CREATEDATE="2024-09-09" UPDATEDATE="2024-09-09" /><OBJECT OBJECTID="165126182" OBJECTGUID="55cda6ea-5f36-4f31-ad29-88bf66010494" CHANGEID="600751853" ISACTIVE="1" LEVELID="9" CREATEDATE="2024-09-09" UPDATEDATE="2024-09-09" /><OBJECT OBJECTID="165126183" OBJECTGUID="4398e98c-2725-4b0d-afaa-507afb057375" CHANGEID="600751855" ISACTIVE="1" LEVELID="10" CREATEDATE="2024-09-09" UPDATEDATE="2024-09-09" /><OBJECT OBJECTID="165126179" OBJECTGUID="74621c6a-cc3f-4b81-90e6-6ec25e6de416" CHANGEID="600751850" ISACTIVE="1" LEVELID="9" CREATEDATE="2024-09-09" UPDATEDATE="2024-09-09" /><OBJECT OBJECTID="165126181" OBJECTGUID="82f0d22c-8c91-441f-9f22-51e803006cff" CHANGEID="600751852" ISACTIVE="1" LEVELID="9" CREATEDATE="2024-09-09" UPDATEDATE="2024-09-09" /><OBJECT OBJECTID="46007508" OBJECTGUID="8782ed91-e71d-413b-be6f-ec166d97f5a8" CHANGEID="600751854" ISACTIVE="0" LEVELID="10" CREATEDATE="2019-07-10" UPDATEDATE="2024-09-09" /><OBJECT OBJECTID="165126184" OBJECTGUID="7f864419-c6a3-4568-8657-89134eb4dfaa" CHANGEID="600936673" ISACTIVE="1" LEVELID="9" CREATEDATE="2024-09-09" UPDATEDATE="2024-09-12" /><OBJECT OBJECTID="165127525" OBJECTGUID="4bea546c-284d-4677-944d-699c56229de4" CHANGEID="600754441" ISACTIVE="1" LEVELID="9" CREATEDATE="2024-09-09" UPDATEDATE="2024-09-09" /><OBJECT OBJECTID="165128546" OBJECTGUID="29b4a9e8-1012-46e8-99f3-7259b712ef8f" CHANGEID="600756025" ISACTIVE="1" LEVELID="9" CREATEDATE="2024-09-09" UPDATEDATE="2024-09-09" /><OBJECT OBJECTID="165131891" OBJECTGUID="f41c956e-fdc8-498e-a5fd-dca75092bccc" CHANGEID="600761463" ISACTIVE="1" LEVELID="10" CREATEDATE="2024-09-09" UPDATEDATE="2024-09-09" /><OBJECT OBJECTID="165132110" OBJECTGUID="3c4a0c91-34a1-49be-bf2f-9225c8112440" CHANGEID="600761697" ISACTIVE="1" LEVELID="9" CREATEDATE="2024-09-09" UPDATEDATE="2024-09-09" /><OBJECT OBJECTID="165132126" OBJECTGUID="b9ee7b10-5d85-4878-8d1e-8888331165e8" CHANGEID="600761728" ISACTIVE="1" LEVELID="10" CREATEDATE="2024-09-09" UPDATEDATE="2024-09-09" /><OBJECT OBJECTID="165132156" OBJECTGUID="b279fae1-c9d0-41eb-9c51-2e8c6fcaea15" CHANGEID="600761761" ISACTIVE="1" LEVELID="9" CREATEDATE="2024-09-09" UPDATEDATE="2024-09-09" /><OBJECT OBJECTID="165133169" OBJECTGUID="6256c375-0c2a-4e3a-a88e-ec8db53e29c2" CHANGEID="600763170" ISACTIVE="1" LEVELID="11" CREATEDATE="2024-09-09" UPDATEDATE="2024-09-09" /><OBJECT OBJECTID="165133171" OBJECTGUID="fc7b84b0-a210-4500-a126-95ac1ce67352" CHANGEID="600763172" ISACTIVE="1" LEVELID="11" CREATEDATE="2024-09-09" UPDATEDATE="2024-09-09" /><OBJECT OBJECTID="165133170" OBJECTGUID="98308a84-c38a-48ea-ae64-74bf95b47720" CHANGEID="600763171" ISACTIVE="1" LEVELID="11" CREATEDATE="2024-09-09" UPDATEDATE="2024-09-09" /><OBJECT OBJECTID="165133172" OBJECTGUID="3367144a-0855-4a7d-98eb-0b449747c684" CHANGEID="600763173" ISACTIVE="1" LEVELID="11" CREATEDATE="2024-09-09" UPDATEDATE="2024-09-09" /><OBJECT OBJECTID="86694986" OBJECTGUID="6840440b-8ac3-42a3-924e-c039ccc8906b" CHANGEID="600763238" ISACTIVE="1" LEVELID="9" CREATEDATE="2018-06-13" UPDATEDATE="2024-09-09" /><OBJECT OBJECTID="165133254" OBJECTGUID="ba1148d4-0de5-4d76-a85b-ccce60850206" CHANGEID="600763269" ISACTIVE="1" LEVELID="10" CREATEDATE="2024-09-09" UPDATEDATE="2024-09-09" /><OBJECT OBJECTID="165133262" OBJECTGUID="893e8507-5ef7-4a5e-aa9e-708f6419c9da" CHANGEID="600763282" ISACTIVE="1" LEVELID="9" CREATEDATE="2024-09-09" UPDATEDATE="2024-09-09" /><OBJECT OBJECTID="165133289" OBJECTGUID="21025d4d-6694-440a-b4b7-3557edc0e3fe" CHANGEID="600763322" ISACTIVE="1" LEVELID="10" CREATEDATE="2024-09-09" UPDATEDATE="2024-09-09" /><OBJECT OBJECTID="165133448" OBJECTGUID="b8107e42-81c6-4852-8907-12b9df2cd964" CHANGEID="600763517" ISACTIVE="1" LEVELID="9" CREATEDATE="2024-09-09" UPDATEDATE="2024-09-09" /><OBJECT OBJECTID="164473101" OBJECTGUID="f04f2fd4-64c8-42ee-b07a-3eafc540bc49" CHANGEID="600860008" ISACTIVE="1" LEVELID="10" CREATEDATE="2024-07-30" UPDATEDATE="2024-09-11" /><OBJECT OBJECTID="164473053" OBJECTGUID="6caa3e4e-e79c-46bf-b2d8-b5ab481088f7" CHANGEID="600860011" ISACTIVE="1" LEVELID="10" CREATEDATE="2024-07-30" UPDATEDATE="2024-09-11" /><OBJECT OBJECTID="164473094" OBJECTGUID="78091bcd-c0fc-4119-8c66-5b5a703bf25b" CHANGEID="600860009" ISACTIVE="1" LEVELID="10" CREATEDATE="2024-07-30" UPDATEDATE="2024-09-11" /><OBJECT OBJECTID="164473085" OBJECTGUID="aa9b1cee-7135-4313-affd-79dd861a37c3" CHANGEID="600860010" ISACTIVE="1" LEVELID="10" CREATEDATE="2024-07-30" UPDATEDATE="2024-09-11" /><OBJECT OBJECTID="164473143" OBJECTGUID="567410a2-e0b2-4a11-a346-03593117627d" CHANGEID="600860005" ISACTIVE="1" LEVELID="10" CREATEDATE="2024-07-30" UPDATEDATE="2024-09-11" /><OBJECT OBJECTID="164473121" OBJECTGUID="92544595-a0fb-4afb-9899-0d06cbe8664e" CHANGEID="600860006" ISACTIVE="1" LEVELID="10" CREATEDATE="2024-07-30" UPDATEDATE="2024-09-11" /><OBJECT OBJECTID="164473114" OBJECTGUID="a8acd373-36a0-4d0f-95d7-e13c992f2075" CHANGEID="600860007" ISACTIVE="1" LEVELID="10" CREATEDATE="2024-07-30" UPDATEDATE="2024-09-11" /><OBJECT OBJECTID="164473156" OBJECTGUID="b328593b-198b-456c-bf89-268526902587" CHANGEID="600860004" ISACTIVE="1" LEVELID="10" CREATEDATE="2024-07-30" UPDATEDATE="2024-09-11" /><OBJECT OBJECTID="165135720" OBJECTGUID="64316f54-6e0d-4b21-be74-04be8cef17b9" CHANGEID="600766593" ISACTIVE="1" LEVELID="9" CREATEDATE="2024-09-09" UPDATEDATE="2024-09-09" /><OBJECT OBJECTID="165135722" OBJECTGUID="5d87cbd3-5753-4304-94a4-e39a804b22a7" CHANGEID="600766595" ISACTIVE="1" LEVELID="9" CREATEDATE="2024-09-09" UPDATEDATE="2024-09-09" /><OBJECT OBJECTID="165135719" OBJECTGUID="c108d0fb-afe0-4741-a87a-562a66c45b75" CHANGEID="600766592" ISACTIVE="1" LEVELID="10" CREATEDATE="2024-09-09" UPDATEDATE="2024-09-09" /><OBJECT OBJECTID="165135721" OBJECTGUID="4937f6f5-303f-4743-93b4-b50a60aeeb3c" CHANGEID="600766594" ISACTIVE="1" LEVELID="10" CREATEDATE="2024-09-09" UPDATEDATE="2024-09-09" /><OBJECT OBJECTID="165135723" OBJECTGUID="597c575e-e1f6-4900-a9f7-fe739c2dc3bd" CHANGEID="600766596" ISACTIVE="1" LEVELID="9" CREATEDATE="2024-09-09" UPDATEDATE="2024-09-09" /><OBJECT OBJECTID="165137403" OBJECTGUID="1c804df1-04fc-4c2d-b52c-54e4b3d3064f" CHANGEID="600770400" ISACTIVE="1" LEVELID="10" CREATEDATE="2024-09-09" UPDATEDATE="2024-09-09" /><OBJECT OBJECTID="165137404" OBJECTGUID="6bcde847-6ac5-4978-96c5-a4fb6d323990" CHANGEID="600770401" ISACTIVE="1" LEVELID="10" CREATEDATE="2024-09-09" UPDATEDATE="2024-09-09" /><OBJECT OBJECTID="165137406" OBJECTGUID="b0ca09c6-83a1-4974-b51c-99de173048ee" CHANGEID="600770403" ISACTIVE="1" LEVELID="9" CREATEDATE="2024-09-09" UPDATEDATE="2024-09-09" /><OBJECT OBJECTID="32680496" OBJECTGUID="4d399a96-c394-44dd-a323-66d73e553b60" CHANGEID="600773129" ISACTIVE="1" LEVELID="10" CREATEDATE="2019-07-10" UPDATEDATE="2024-09-09" /><OBJECT OBJECTID="165141474" OBJECTGUID="48cd895c-e5b2-4afe-806e-7e59feb384a3" CHANGEID="600776583" ISACTIVE="1" LEVELID="10" CREATEDATE="2024-09-09" UPDATEDATE="2024-09-09" /><OBJECT OBJECTID="165141475" OBJECTGUID="8abae162-13c4-4061-8cb0-be0b319b8458" CHANGEID="600776584" ISACTIVE="1" LEVELID="10" CREATEDATE="2024-09-09" UPDATEDATE="2024-09-09" /><OBJECT OBJECTID="64657157" OBJECTGUID="4e9f21ac-cf03-4f19-8e3a-9e85baf970e2" CHANGEID="600776587" ISACTIVE="1" LEVELID="10" CREATEDATE="2017-12-18" UPDATEDATE="2024-09-09" /><OBJECT OBJECTID="165141506" OBJECTGUID="8643acb1-1f2e-43bf-9d19-f3efad8a5cb6" CHANGEID="600776677" ISACTIVE="1" LEVELID="9" CREATEDATE="2024-09-09" UPDATEDATE="2024-09-09" /><OBJECT OBJECTID="165141551" OBJECTGUID="0900a0e3-ff29-4f87-8a1a-6d83e568a325" CHANGEID="600776757" ISACTIVE="1" LEVELID="9" CREATEDATE="2024-09-09" UPDATEDATE="2024-09-09" /><OBJECT OBJECTID="165146327" OBJECTGUID="f22cf4c0-3fd7-42a5-bd38-0764870f4464" CHANGEID="600784770" ISACTIVE="1" LEVELID="9" CREATEDATE="2024-09-09" UPDATEDATE="2024-09-09" /><OBJECT OBJECTID="165162666" OBJECTGUID="b7e724d9-e1d8-45ca-9b74-c26f64a79d09" CHANGEID="600815142" ISACTIVE="1" LEVELID="9" CREATEDATE="2024-09-10" UPDATEDATE="2024-09-10" /><OBJECT OBJECTID="76324144" OBJECTGUID="4f104bb2-02dc-47e1-ab97-b0d76193cfdf" CHANGEID="600797425" ISACTIVE="0" LEVELID="10" CREATEDATE="2017-12-18" UPDATEDATE="2024-09-10" /><OBJECT OBJECTID="165151787" OBJECTGUID="aa33aa79-efdf-4306-a1f7-afad41bf699b" CHANGEID="600797440" ISACTIVE="1" LEVELID="10" CREATEDATE="2024-09-10" UPDATEDATE="2024-09-10" /><OBJECT OBJECTID="165152259" OBJECTGUID="d8c1b821-8192-4b4a-b577-0402be1d2609" CHANGEID="600798144" ISACTIVE="1" LEVELID="10" CREATEDATE="2024-09-10" UPDATEDATE="2024-09-10" /><OBJECT OBJECTID="165152262" OBJECTGUID="a1e7029e-909f-49e1-abef-b5e5fb947afe" CHANGEID="600798147" ISACTIVE="1" LEVELID="9" CREATEDATE="2024-09-10" UPDATEDATE="2024-09-10" /><OBJECT OBJECTID="165152329" OBJECTGUID="1ff0b5f2-0ca8-4a06-aea7-bbcd536fe31c" CHANGEID="600798231" ISACTIVE="1" LEVELID="10" CREATEDATE="2024-09-10" UPDATEDATE="2024-09-10" /><OBJECT OBJECTID="55391215" OBJECTGUID="b1bf3b4d-fe52-4818-acf2-47f0388953e3" CHANGEID="600798233" ISACTIVE="1" LEVELID="11" CREATEDATE="2017-05-04" UPDATEDATE="2024-09-10" /><OBJECT OBJECTID="165152327" OBJECTGUID="30f40153-b6ff-4180-a39f-a833c82a1ff5" CHANGEID="600798213" ISACTIVE="1" LEVELID="9" CREATEDATE="2024-09-10" UPDATEDATE="2024-09-10" /><OBJECT OBJECTID="58685212" OBJECTGUID="6a42f12e-692d-402e-8b6a-aa27892a8cfe" CHANGEID="600798218" ISACTIVE="0" LEVELID="11" CREATEDATE="2018-08-16" UPDATEDATE="2024-09-10" /><OBJECT OBJECTID="55391228" OBJECTGUID="f0d8169f-6655-40c5-a9cb-38418fc1519c" CHANGEID="600798232" ISACTIVE="1" LEVELID="11" CREATEDATE="2017-05-04" UPDATEDATE="2024-09-10" /><OBJECT OBJECTID="165156429" OBJECTGUID="b78a3b5a-480b-44d3-a94b-608aec23879a" CHANGEID="600804835" ISACTIVE="1" LEVELID="9" CREATEDATE="2024-09-10" UPDATEDATE="2024-09-10" /><OBJECT OBJECTID="165156436" OBJECTGUID="b12ed9f8-4f04-4ff3-910d-09f1f5e908b8" CHANGEID="600804846" ISACTIVE="1" LEVELID="10" CREATEDATE="2024-09-10" UPDATEDATE="2024-09-10" /><OBJECT OBJECTID="165156450" OBJECTGUID="9830cf75-e848-4204-ac28-f5eb7f6381d8" CHANGEID="600804862" ISACTIVE="1" LEVELID="9" CREATEDATE="2024-09-10" UPDATEDATE="2024-09-10" /><OBJECT OBJECTID="165156451" OBJECTGUID="c4995b73-86b9-403d-a135-46152fcf98db" CHANGEID="600804866" ISACTIVE="1" LEVELID="10" CREATEDATE="2024-09-10" UPDATEDATE="2024-09-10" /><OBJECT OBJECTID="165156661" OBJECTGUID="b44c121c-311b-4a70-94c3-b9c103b67f98" CHANGEID="600805107" ISACTIVE="1" LEVELID="10" CREATEDATE="2024-09-10" UPDATEDATE="2024-09-10" /><OBJECT OBJECTID="165156687" OBJECTGUID="00fe36bf-78aa-495d-800e-418dd3e2b2ed" CHANGEID="600805134" ISACTIVE="1" LEVELID="9" CREATEDATE="2024-09-10" UPDATEDATE="2024-09-10" /><OBJECT OBJECTID="165156820" OBJECTGUID="b05f185c-d109-44b2-a40b-0e76de7542dd" CHANGEID="600805271" ISACTIVE="1" LEVELID="9" CREATEDATE="2024-09-10" UPDATEDATE="2024-09-10" /><OBJECT OBJECTID="165156874" OBJECTGUID="f8efbade-4147-4ca5-84df-3f8315f0017c" CHANGEID="600805374" ISACTIVE="1" LEVELID="9" CREATEDATE="2024-09-10" UPDATEDATE="2024-09-10" /><OBJECT OBJECTID="44331847" OBJECTGUID="74009db6-14ae-4bf0-a393-35e9e8d4d426" CHANGEID="600805585" ISACTIVE="0" LEVELID="10" CREATEDATE="2017-12-18" UPDATEDATE="2024-09-10" /><OBJECT OBJECTID="165157064" OBJECTGUID="8e636b58-c004-4460-ab76-20c6cc1550db" CHANGEID="600806131" ISACTIVE="1" LEVELID="9" CREATEDATE="2024-09-10" UPDATEDATE="2024-09-10" /><OBJECT OBJECTID="165157066" OBJECTGUID="b1fb3070-204b-4e62-bc65-1ff13fe4e8ab" CHANGEID="600806133" ISACTIVE="1" LEVELID="9" CREATEDATE="2024-09-10" UPDATEDATE="2024-09-10" /><OBJECT OBJECTID="165157068" OBJECTGUID="6427ca30-590f-4d21-aa9c-52d0839f659e" CHANGEID="600806135" ISACTIVE="1" LEVELID="9" CREATEDATE="2024-09-10" UPDATEDATE="2024-09-10" /><OBJECT OBJECTID="165157070" OBJECTGUID="4f699435-ce7b-4d50-919e-e13c8e2c8ff0" CHANGEID="600806137" ISACTIVE="1" LEVELID="9" CREATEDATE="2024-09-10" UPDATEDATE="2024-09-10" /><OBJECT OBJECTID="165157072" OBJECTGUID="cd55abc2-818a-4a15-a804-50765e7e1297" CHANGEID="600806139" ISACTIVE="1" LEVELID="9" CREATEDATE="2024-09-10" UPDATEDATE="2024-09-10" /><OBJECT OBJECTID="165157074" OBJECTGUID="b3eb92b8-7d1f-4eaf-adce-d664ee1b5fa8" CHANGEID="600806141" ISACTIVE="1" LEVELID="9" CREATEDATE="2024-09-10" UPDATEDATE="2024-09-10" /><OBJECT OBJECTID="165157076" OBJECTGUID="c7c17f4c-2fa3-4578-9fde-fd2776cad5f5" CHANGEID="600806143" ISACTIVE="1" LEVELID="9" CREATEDATE="2024-09-10" UPDATEDATE="2024-09-10" /><OBJECT OBJECTID="165157078" OBJECTGUID="91617445-7688-47c6-9a6b-40bcd61c2090" CHANGEID="600806145" ISACTIVE="1" LEVELID="9" CREATEDATE="2024-09-10" UPDATEDATE="2024-09-10" /><OBJECT OBJECTID="165157081" OBJECTGUID="237fbbfe-d9bf-4b10-9af6-58f9efe5a942" CHANGEID="600806165" ISACTIVE="1" LEVELID="9" CREATEDATE="2024-09-10" UPDATEDATE="2024-09-10" /><OBJECT OBJECTID="165157063" OBJECTGUID="74728c7f-4c66-4258-82f9-3b7ceb953239" CHANGEID="600806130" ISACTIVE="1" LEVELID="9" CREATEDATE="2024-09-10" UPDATEDATE="2024-09-10" /><OBJECT OBJECTID="165157065" OBJECTGUID="3e61988c-2182-46af-be4b-d78f51c76cbb" CHANGEID="600806132" ISACTIVE="1" LEVELID="9" CREATEDATE="2024-09-10" UPDATEDATE="2024-09-10" /><OBJECT OBJECTID="165157067" OBJECTGUID="2d9cd504-9249-4467-8d8f-af5d278ae12f" CHANGEID="600806134" ISACTIVE="1" LEVELID="9" CREATEDATE="2024-09-10" UPDATEDATE="2024-09-10" /><OBJECT OBJECTID="165157069" OBJECTGUID="1dc98f73-36f1-436d-be7c-f838283370c9" CHANGEID="600806136" ISACTIVE="1" LEVELID="9" CREATEDATE="2024-09-10" UPDATEDATE="2024-09-10" /><OBJECT OBJECTID="165157071" OBJECTGUID="f77659ad-99ed-4803-ae4a-7c809a35f9ef" CHANGEID="600806138" ISACTIVE="1" LEVELID="9" CREATEDATE="2024-09-10" UPDATEDATE="2024-09-10" /><OBJECT OBJECTID="165157073" OBJECTGUID="9e68bd1b-1b22-4b5b-bb36-bd8745b97040" CHANGEID="600806140" ISACTIVE="1" LEVELID="9" CREATEDATE="2024-09-10" UPDATEDATE="2024-09-10" /><OBJECT OBJECTID="165157075" OBJECTGUID="146f61a3-37d0-4050-a14e-42e1a0a563d4" CHANGEID="600806142" ISACTIVE="1" LEVELID="9" CREATEDATE="2024-09-10" UPDATEDATE="2024-09-10" /><OBJECT OBJECTID="165157077" OBJECTGUID="1d78eb81-b6a5-4931-938a-a323da8f3de9" CHANGEID="600806144" ISACTIVE="1" LEVELID="9" CREATEDATE="2024-09-10" UPDATEDATE="2024-09-10" /><OBJECT OBJECTID="165157079" OBJECTGUID="c7f7039d-dd84-427c-991f-7bb65299937a" CHANGEID="600806146" ISACTIVE="1" LEVELID="9" CREATEDATE="2024-09-10" UPDATEDATE="2024-09-10" /><OBJECT OBJECTID="165157080" OBJECTGUID="cf61c98b-4593-445a-bc18-9bbc1aff0395" CHANGEID="600806152" ISACTIVE="1" LEVELID="9" CREATEDATE="2024-09-10" UPDATEDATE="2024-09-10" /><OBJECT OBJECTID="165157082" OBJECTGUID="a76b1ee7-97ce-4295-9407-ae18cbf5f6c4" CHANGEID="600806167" ISACTIVE="1" LEVELID="10" CREATEDATE="2024-09-10" UPDATEDATE="2024-09-10" /><OBJECT OBJECTID="165157714" OBJECTGUID="1ebed52f-28b9-4ad1-a75c-a77b42bd3c3f" CHANGEID="600807256" ISACTIVE="1" LEVELID="10" CREATEDATE="2024-09-10" UPDATEDATE="2024-09-10" /><OBJECT OBJECTID="165157951" OBJECTGUID="b96a2869-7556-4d8a-bd4d-ec65afc5327d" CHANGEID="600807681" ISACTIVE="1" LEVELID="9" CREATEDATE="2024-09-10" UPDATEDATE="2024-09-10" /><OBJECT OBJECTID="71905354" OBJECTGUID="5b04bc0e-b3e6-420e-a8aa-4b3e77737873" CHANGEID="600807689" ISACTIVE="0" LEVELID="10" CREATEDATE="2017-12-18" UPDATEDATE="2024-09-10" /><OBJECT OBJECTID="165157952" OBJECTGUID="fe04d508-89aa-4cb4-87cf-b08b49438220" CHANGEID="600807694" ISACTIVE="1" LEVELID="10" CREATEDATE="2024-09-10" UPDATEDATE="2024-09-10" /><OBJECT OBJECTID="165157955" OBJECTGUID="d67f24b3-f245-4b64-8280-a1b1d015622d" CHANGEID="600807702" ISACTIVE="1" LEVELID="11" CREATEDATE="2024-09-10" UPDATEDATE="2024-09-10" /><OBJECT OBJECTID="165157958" OBJECTGUID="14fe0ccf-4f68-444e-aaae-9b4010c1ff30" CHANGEID="600807723" ISACTIVE="1" LEVELID="9" CREATEDATE="2024-09-10" UPDATEDATE="2024-09-10" /><OBJECT OBJECTID="165157954" OBJECTGUID="d1c6e1c6-bbcc-461d-b5ac-0256369741d6" CHANGEID="600832086" ISACTIVE="1" LEVELID="10" CREATEDATE="2024-09-10" UPDATEDATE="2024-09-10" /><OBJECT OBJECTID="165157978" OBJECTGUID="14f707a5-58d1-444e-b221-87933306829f" CHANGEID="600807775" ISACTIVE="1" LEVELID="9" CREATEDATE="2024-09-10" UPDATEDATE="2024-09-10" /><OBJECT OBJECTID="165157979" OBJECTGUID="fef8a165-052e-48b2-88b1-c4050d4388e2" CHANGEID="600807777" ISACTIVE="1" LEVELID="9" CREATEDATE="2024-09-10" UPDATEDATE="2024-09-10" /><OBJECT OBJECTID="165158320" OBJECTGUID="3a32d0ee-8f45-48c6-964b-7a2c90f7fa5c" CHANGEID="600808286" ISACTIVE="1" LEVELID="10" CREATEDATE="2024-09-10" UPDATEDATE="2024-09-10" /><OBJECT OBJECTID="165158324" OBJECTGUID="12beb79e-6bbe-44cb-a6d2-e84414cdd074" CHANGEID="600808290" ISACTIVE="1" LEVELID="11" CREATEDATE="2024-09-10" UPDATEDATE="2024-09-10" /><OBJECT OBJECTID="164532864" OBJECTGUID="06112c56-3cf7-4729-ab1d-5cce3bfa6b1c" CHANGEID="600860003" ISACTIVE="1" LEVELID="10" CREATEDATE="2024-08-05" UPDATEDATE="2024-09-11" /><OBJECT OBJECTID="165159628" OBJECTGUID="fd11d737-cceb-4df5-a8bd-fc5c5fcf38ae" CHANGEID="600810525" ISACTIVE="1" LEVELID="11" CREATEDATE="2024-09-10" UPDATEDATE="2024-09-10" /><OBJECT OBJECTID="165159627" OBJECTGUID="4209ab52-cece-4db5-be01-b1af3eaaacfe" CHANGEID="600810524" ISACTIVE="1" LEVELID="11" CREATEDATE="2024-09-10" UPDATEDATE="2024-09-10" /><OBJECT OBJECTID="165159637" OBJECTGUID="520e3d34-6afb-4b19-8b89-7f3ef269de82" CHANGEID="600810534" ISACTIVE="1" LEVELID="10" CREATEDATE="2024-09-10" UPDATEDATE="2024-09-10" /><OBJECT OBJECTID="165167441" OBJECTGUID="d03f58be-a5f8-475d-bdb3-a164852aa6e7" CHANGEID="600822970" ISACTIVE="1" LEVELID="10" CREATEDATE="2024-09-10" UPDATEDATE="2024-09-10" /><OBJECT OBJECTID="165167659" OBJECTGUID="84de00d8-6113-456a-b1f0-7f43b85e1cf3" CHANGEID="600823299" ISACTIVE="1" LEVELID="10" CREATEDATE="2024-09-10" UPDATEDATE="2024-09-10" /><OBJECT OBJECTID="79284655" OBJECTGUID="f4e1beb3-12cf-4232-9405-4824a5d5313b" CHANGEID="600830195" ISACTIVE="0" LEVELID="11" CREATEDATE="2018-08-27" UPDATEDATE="2024-09-10" /><OBJECT OBJECTID="165173465" OBJECTGUID="6715b6b6-0b87-42a5-8c73-2c95a2954756" CHANGEID="600832302" ISACTIVE="1" LEVELID="9" CREATEDATE="2024-09-10" UPDATEDATE="2024-09-10" /><OBJECT OBJECTID="165173517" OBJECTGUID="ba06bcee-bbf1-4a3b-ac4e-4f2e6d1c5fca" CHANGEID="600832357" ISACTIVE="1" LEVELID="9" CREATEDATE="2024-09-10" UPDATEDATE="2024-09-10" /><OBJECT OBJECTID="165176903" OBJECTGUID="e3871edb-26b6-4a00-936d-cf46c334db25" CHANGEID="600837200" ISACTIVE="1" LEVELID="9" CREATEDATE="2024-09-10" UPDATEDATE="2024-09-10" /><OBJECT OBJECTID="165178049" OBJECTGUID="3570e4ed-6d54-489f-9040-9219c28cb2ae" CHANGEID="600838914" ISACTIVE="1" LEVELID="9" CREATEDATE="2024-09-10" UPDATEDATE="2024-09-10" /><OBJECT OBJECTID="165178247" OBJECTGUID="c12fbb77-4707-4a80-bbe9-f0aca0884f71" CHANGEID="600839235" ISACTIVE="1" LEVELID="9" CREATEDATE="2024-09-10" UPDATEDATE="2024-09-10" /><OBJECT OBJECTID="165178256" OBJECTGUID="b4489ad2-5db0-4c06-810e-1febb09392fd" CHANGEID="600839251" ISACTIVE="1" LEVELID="10" CREATEDATE="2024-09-10" UPDATEDATE="2024-09-10" /><OBJECT OBJECTID="165179146" OBJECTGUID="6388b53f-9757-4fda-9f04-3bf8a5b554cd" CHANGEID="600840802" ISACTIVE="1" LEVELID="9" CREATEDATE="2024-09-10" UPDATEDATE="2024-09-10" /><OBJECT OBJECTID="165179390" OBJECTGUID="3214b2f1-5c06-4192-bdf4-7825929315ae" CHANGEID="600841330" ISACTIVE="1" LEVELID="10" CREATEDATE="2024-09-10" UPDATEDATE="2024-09-10" /><OBJECT OBJECTID="165179433" OBJECTGUID="b4c08dd7-f2e3-421f-903a-f0eb63688c5d" CHANGEID="600841396" ISACTIVE="1" LEVELID="9" CREATEDATE="2024-09-10" UPDATEDATE="2024-09-10" /><OBJECT OBJECTID="165179429" OBJECTGUID="e23eb40d-7b4b-45fa-b49c-29d55f06d7ca" CHANGEID="600841387" ISACTIVE="1" LEVELID="10" CREATEDATE="2024-09-10" UPDATEDATE="2024-09-10" /><OBJECT OBJECTID="164573969" OBJECTGUID="f9ea1cf0-7618-42c8-9fa2-5a9a4edbb97c" CHANGEID="600860001" ISACTIVE="1" LEVELID="10" CREATEDATE="2024-08-07" UPDATEDATE="2024-09-11" /><OBJECT OBJECTID="164573968" OBJECTGUID="ea29400e-4dd8-43dd-8f28-970ab9b6b18a" CHANGEID="600860002" ISACTIVE="1" LEVELID="10" CREATEDATE="2024-08-07" UPDATEDATE="2024-09-11" /><OBJECT OBJECTID="165208817" OBJECTGUID="0d4e1435-c92c-4157-9a92-34151a121b8e" CHANGEID="600910000" ISACTIVE="1" LEVELID="9" CREATEDATE="2024-09-11" UPDATEDATE="2024-09-11" /><OBJECT OBJECTID="164079520" OBJECTGUID="e92be608-9d97-46be-90ad-241ecede4af3" CHANGEID="600859907" ISACTIVE="1" LEVELID="10" CREATEDATE="2024-07-02" UPDATEDATE="2024-09-11" /><OBJECT OBJECTID="164079518" OBJECTGUID="37010541-7637-439a-b353-e5eb9b11a83f" CHANGEID="600859908" ISACTIVE="1" LEVELID="10" CREATEDATE="2024-07-02" UPDATEDATE="2024-09-11" /><OBJECT OBJECTID="164033105" OBJECTGUID="94846aa5-49a8-4524-8839-8a1bed657b63" CHANGEID="600859910" ISACTIVE="1" LEVELID="10" CREATEDATE="2024-06-27" UPDATEDATE="2024-09-11" /><OBJECT OBJECTID="164033103" OBJECTGUID="197de5d3-4bbe-45d3-9c2e-fea858f59a2d" CHANGEID="600859911" ISACTIVE="1" LEVELID="10" CREATEDATE="2024-06-27" UPDATEDATE="2024-09-11" /><OBJECT OBJECTID="164033101" OBJECTGUID="89c16da1-e100-4dcb-9f83-3aef0c5a5359" CHANGEID="600859912" ISACTIVE="1" LEVELID="10" CREATEDATE="2024-06-27" UPDATEDATE="2024-09-11" /><OBJECT OBJECTID="164885474" OBJECTGUID="1318f8c4-e79a-4376-be9e-c74f61c7755c" CHANGEID="600860099" ISACTIVE="1" LEVELID="10" CREATEDATE="2024-08-27" UPDATEDATE="2024-09-11" /><OBJECT OBJECTID="164885473" OBJECTGUID="b646d9d9-3741-40ee-b140-68a61bb2c1ab" CHANGEID="600860100" ISACTIVE="1" LEVELID="10" CREATEDATE="2024-08-27" UPDATEDATE="2024-09-11" /><OBJECT OBJECTID="164885472" OBJECTGUID="7ea78a9a-8f7f-4387-9b4b-404012ec5e65" CHANGEID="600860101" ISACTIVE="1" LEVELID="10" CREATEDATE="2024-08-27" UPDATEDATE="2024-09-11" /><OBJECT OBJECTID="164885471" OBJECTGUID="47048d9a-a065-4962-9d76-e27712ed924f" CHANGEID="600860102" ISACTIVE="1" LEVELID="10" CREATEDATE="2024-08-27" UPDATEDATE="2024-09-11" /><OBJECT OBJECTID="164885470" OBJECTGUID="6e455b04-1cba-4389-88c3-a93f2d81b60b" CHANGEID="600860103" ISACTIVE="1" LEVELID="10" CREATEDATE="2024-08-27" UPDATEDATE="2024-09-11" /><OBJECT OBJECTID="164885469" OBJECTGUID="ad794b34-51ff-49a8-8159-215f76d895c3" CHANGEID="600860104" ISACTIVE="1" LEVELID="10" CREATEDATE="2024-08-27" UPDATEDATE="2024-09-11" /><OBJECT OBJECTID="164885125" OBJECTGUID="b790a727-fb4e-4962-9fdb-18e7f974e06f" CHANGEID="600860105" ISACTIVE="1" LEVELID="10" CREATEDATE="2024-08-27" UPDATEDATE="2024-09-11" /><OBJECT OBJECTID="164884863" OBJECTGUID="c88ddf61-237c-4a0d-bdd3-08935273c386" CHANGEID="600860106" ISACTIVE="1" LEVELID="10" CREATEDATE="2024-08-27" UPDATEDATE="2024-09-11" /><OBJECT OBJECTID="164884862" OBJECTGUID="6dc720d7-0d8c-4957-9992-29215eabb32d" CHANGEID="600860107" ISACTIVE="1" LEVELID="10" CREATEDATE="2024-08-27" UPDATEDATE="2024-09-11" /><OBJECT OBJECTID="164884861" OBJECTGUID="e824bd10-a99d-4305-94aa-ea1561a53bf1" CHANGEID="600860108" ISACTIVE="1" LEVELID="10" CREATEDATE="2024-08-27" UPDATEDATE="2024-09-11" /><OBJECT OBJECTID="164884860" OBJECTGUID="92939235-ad99-4166-9f9e-8f57c87f5eb9" CHANGEID="600860109" ISACTIVE="1" LEVELID="10" CREATEDATE="2024-08-27" UPDATEDATE="2024-09-11" /><OBJECT OBJECTID="164863042" OBJECTGUID="4344fbcd-5595-429f-a0fa-12cdac5b77dd" CHANGEID="600860110" ISACTIVE="1" LEVELID="10" CREATEDATE="2024-08-26" UPDATEDATE="2024-09-11" /><OBJECT OBJECTID="164411854" OBJECTGUID="d13aefb5-007d-4d5a-86ba-37bc4e61369b" CHANGEID="600859928" ISACTIVE="1" LEVELID="10" CREATEDATE="2024-07-25" UPDATEDATE="2024-09-11" /><OBJECT OBJECTID="164310379" OBJECTGUID="b3fc8415-5a13-492f-b9e3-a3118917781e" CHANGEID="600859930" ISACTIVE="1" LEVELID="10" CREATEDATE="2024-07-18" UPDATEDATE="2024-09-11" /><OBJECT OBJECTID="164654771" OBJECTGUID="0a83a357-6ca0-4259-8449-9704f5031d91" CHANGEID="600859998" ISACTIVE="1" LEVELID="10" CREATEDATE="2024-08-13" UPDATEDATE="2024-09-11" /><OBJECT OBJECTID="164654768" OBJECTGUID="66f6dc50-393b-43aa-ab0f-635dfea752d2" CHANGEID="600860000" ISACTIVE="1" LEVELID="10" CREATEDATE="2024-08-13" UPDATEDATE="2024-09-11" /><OBJECT OBJECTID="165209107" OBJECTGUID="4ed934f6-c313-44da-9aa0-6aca44230d22" CHANGEID="600910592" ISACTIVE="1" LEVELID="9" CREATEDATE="2024-09-11" UPDATEDATE="2024-09-11" /><OBJECT OBJECTID="165184586" OBJECTGUID="10d1d10a-32c8-44ac-bf78-6f233c377d79" CHANGEID="600873959" ISACTIVE="1" LEVELID="9" CREATEDATE="2024-09-11" UPDATEDATE="2024-09-11" /><OBJECT OBJECTID="165184673" OBJECTGUID="0302c431-1a7b-4d7b-9294-c6a77586e31a" CHANGEID="600874202" ISACTIVE="1" LEVELID="9" CREATEDATE="2024-09-11" UPDATEDATE="2024-09-11" /><OBJECT OBJECTID="165186071" OBJECTGUID="e8a5cc45-7a51-4472-91fa-9cd6a57bc97e" CHANGEID="600877060" ISACTIVE="1" LEVELID="9" CREATEDATE="2024-09-11" UPDATEDATE="2024-09-11" /><OBJECT OBJECTID="165186728" OBJECTGUID="546522a3-075d-4023-a2f3-59701480549a" CHANGEID="600877962" ISACTIVE="1" LEVELID="9" CREATEDATE="2024-09-11" UPDATEDATE="2024-09-11" /><OBJECT OBJECTID="165186784" OBJECTGUID="6287ccad-18c6-45f5-aa1a-ea4a6d3e0456" CHANGEID="600878069" ISACTIVE="1" LEVELID="10" CREATEDATE="2024-09-11" UPDATEDATE="2024-09-11" /><OBJECT OBJECTID="165186924" OBJECTGUID="0fc8fa45-c72e-4894-874f-8681f8797621" CHANGEID="600878309" ISACTIVE="1" LEVELID="10" CREATEDATE="2024-09-11" UPDATEDATE="2024-09-11" /><OBJECT OBJECTID="165186932" OBJECTGUID="0365ab9f-a8fd-4eb9-afd5-811965f60f89" CHANGEID="600878318" ISACTIVE="1" LEVELID="9" CREATEDATE="2024-09-11" UPDATEDATE="2024-09-11" /><OBJECT OBJECTID="165186936" OBJECTGUID="5a02173f-0844-4353-8c23-77323a040719" CHANGEID="600878323" ISACTIVE="1" LEVELID="9" CREATEDATE="2024-09-11" UPDATEDATE="2024-09-11" /><OBJECT OBJECTID="165186939" OBJECTGUID="41c27c13-ecd4-484d-8336-16725a51778a" CHANGEID="600878327" ISACTIVE="1" LEVELID="9" CREATEDATE="2024-09-11" UPDATEDATE="2024-09-11" /><OBJECT OBJECTID="165186942" OBJECTGUID="747bbad3-f491-4844-a027-8e9d233c9b46" CHANGEID="600878331" ISACTIVE="1" LEVELID="9" CREATEDATE="2024-09-11" UPDATEDATE="2024-09-11" /><OBJECT OBJECTID="165186944" OBJECTGUID="98344156-7826-4c5f-ae94-48e56cdebb65" CHANGEID="600878333" ISACTIVE="1" LEVELID="9" CREATEDATE="2024-09-11" UPDATEDATE="2024-09-11" /><OBJECT OBJECTID="165186931" OBJECTGUID="ec2c273d-e8c5-4942-9960-c3c6ccbd9aa9" CHANGEID="600878317" ISACTIVE="1" LEVELID="9" CREATEDATE="2024-09-11" UPDATEDATE="2024-09-11" /><OBJECT OBJECTID="165186935" OBJECTGUID="4c3550c5-c50a-4c68-8d7a-e114fe068c2d" CHANGEID="600878322" ISACTIVE="1" LEVELID="9" CREATEDATE="2024-09-11" UPDATEDATE="2024-09-11" /><OBJECT OBJECTID="165186937" OBJECTGUID="3c270053-52c8-489d-8326-cf2cd45cbd9a" CHANGEID="600878324" ISACTIVE="1" LEVELID="9" CREATEDATE="2024-09-11" UPDATEDATE="2024-09-11" /><OBJECT OBJECTID="165186938" OBJECTGUID="0b497a3e-a3e6-48de-84b1-ea653be25396" CHANGEID="600878326" ISACTIVE="1" LEVELID="9" CREATEDATE="2024-09-11" UPDATEDATE="2024-09-11" /><OBJECT OBJECTID="165186940" OBJECTGUID="eb8949b4-c264-4229-862a-6347585c856d" CHANGEID="600878328" ISACTIVE="1" LEVELID="9" CREATEDATE="2024-09-11" UPDATEDATE="2024-09-11" /><OBJECT OBJECTID="165186941" OBJECTGUID="cf36e9a6-9e15-4d05-a571-e7925a1c076e" CHANGEID="600878330" ISACTIVE="1" LEVELID="9" CREATEDATE="2024-09-11" UPDATEDATE="2024-09-11" /><OBJECT OBJECTID="165186945" OBJECTGUID="2570b0ef-2169-4198-a0f5-3c7862dc7a54" CHANGEID="600878334" ISACTIVE="1" LEVELID="9" CREATEDATE="2024-09-11" UPDATEDATE="2024-09-11" /><OBJECT OBJECTID="165186946" OBJECTGUID="3b123ab7-30b4-4af3-837d-0678dade05fe" CHANGEID="600878335" ISACTIVE="1" LEVELID="9" CREATEDATE="2024-09-11" UPDATEDATE="2024-09-11" /><OBJECT OBJECTID="165187028" OBJECTGUID="a3282bc3-94d6-4042-90e7-bcaa44e33e0f" CHANGEID="600878450" ISACTIVE="1" LEVELID="9" CREATEDATE="2024-09-11" UPDATEDATE="2024-09-11" /><OBJECT OBJECTID="165187002" OBJECTGUID="37338726-6605-4f19-a7c1-d27b5c97a798" CHANGEID="600878421" ISACTIVE="1" LEVELID="10" CREATEDATE="2024-09-11" UPDATEDATE="2024-09-11" /><OBJECT OBJECTID="165187252" OBJECTGUID="d5ca8232-1fe4-4045-b923-f7975a3dcc05" CHANGEID="600878701" ISACTIVE="1" LEVELID="9" CREATEDATE="2024-09-11" UPDATEDATE="2024-09-11" /><OBJECT OBJECTID="165187593" OBJECTGUID="4d8dd456-e4b1-4dde-ae98-9ff8b25544e1" CHANGEID="600879146" ISACTIVE="1" LEVELID="10" CREATEDATE="2024-09-11" UPDATEDATE="2024-09-11" /><OBJECT OBJECTID="43709914" OBJECTGUID="21df8807-80ac-4464-83c9-83507832d031" CHANGEID="600879148" ISACTIVE="1" LEVELID="10" CREATEDATE="2019-07-10" UPDATEDATE="2024-09-11" /><OBJECT OBJECTID="165187592" OBJECTGUID="a47dbc67-d3b6-4bfe-8155-ae9b3d1eedb5" CHANGEID="600879145" ISACTIVE="1" LEVELID="9" CREATEDATE="2024-09-11" UPDATEDATE="2024-09-11" /><OBJECT OBJECTID="165187594" OBJECTGUID="22f1a08c-9d95-4018-baab-3e232417355a" CHANGEID="600879147" ISACTIVE="1" LEVELID="9" CREATEDATE="2024-09-11" UPDATEDATE="2024-09-11" /><OBJECT OBJECTID="165188543" OBJECTGUID="e9d27a0b-8411-4803-8141-0a97675d2f30" CHANGEID="600880448" ISACTIVE="1" LEVELID="9" CREATEDATE="2024-09-11" UPDATEDATE="2024-09-11" /><OBJECT OBJECTID="165188544" OBJECTGUID="40900574-6409-4d12-bdec-3d72c168f913" CHANGEID="600880449" ISACTIVE="1" LEVELID="9" CREATEDATE="2024-09-11" UPDATEDATE="2024-09-11" /><OBJECT OBJECTID="165188532" OBJECTGUID="4b9dfb05-efc8-4e5e-8045-3c5b15431071" CHANGEID="600880431" ISACTIVE="1" LEVELID="10" CREATEDATE="2024-09-11" UPDATEDATE="2024-09-11" /><OBJECT OBJECTID="165188540" OBJECTGUID="5589436b-def6-46a0-b06e-b5159f60238a" CHANGEID="600880445" ISACTIVE="1" LEVELID="9" CREATEDATE="2024-09-11" UPDATEDATE="2024-09-11" /><OBJECT OBJECTID="165188542" OBJECTGUID="593ca763-b7ab-4f1d-b90a-baec030d1170" CHANGEID="600880447" ISACTIVE="1" LEVELID="10" CREATEDATE="2024-09-11" UPDATEDATE="2024-09-11" /><OBJECT OBJECTID="165189245" OBJECTGUID="1fe0fec4-83de-4c68-a3ac-2038cb28f117" CHANGEID="600881658" ISACTIVE="1" LEVELID="10" CREATEDATE="2024-09-11" UPDATEDATE="2024-09-11" /><OBJECT OBJECTID="165189246" OBJECTGUID="6f214053-9e43-43f5-9c82-5dd9492ff6a6" CHANGEID="600881660" ISACTIVE="1" LEVELID="9" CREATEDATE="2024-09-11" UPDATEDATE="2024-09-11" /><OBJECT OBJECTID="165189244" OBJECTGUID="e06ec53e-6621-4579-8691-6953b1b954e1" CHANGEID="600881657" ISACTIVE="1" LEVELID="9" CREATEDATE="2024-09-11" UPDATEDATE="2024-09-11" /><OBJECT OBJECTID="165189247" OBJECTGUID="8423f8e4-7f3d-4a1a-ad26-24fd954b9821" CHANGEID="600881663" ISACTIVE="1" LEVELID="9" CREATEDATE="2024-09-11" UPDATEDATE="2024-09-11" /><OBJECT OBJECTID="165189248" OBJECTGUID="ee811cc1-8d32-4001-a6f4-c2184a44403b" CHANGEID="600881665" ISACTIVE="1" LEVELID="9" CREATEDATE="2024-09-11" UPDATEDATE="2024-09-11" /><OBJECT OBJECTID="165189249" OBJECTGUID="1a73bc11-9dde-43eb-b16e-c1b1b9309534" CHANGEID="600881667" ISACTIVE="1" LEVELID="9" CREATEDATE="2024-09-11" UPDATEDATE="2024-09-11" /><OBJECT OBJECTID="165189474" OBJECTGUID="c7bacbdb-5e49-41ec-a9f1-ded69e0b3a06" CHANGEID="600882100" ISACTIVE="1" LEVELID="9" CREATEDATE="2024-09-11" UPDATEDATE="2024-09-11" /><OBJECT OBJECTID="165189945" OBJECTGUID="b5e7a09f-dc14-460f-a20b-b5adb4b98b31" CHANGEID="600882712" ISACTIVE="1" LEVELID="9" CREATEDATE="2024-09-11" UPDATEDATE="2024-09-11" /><OBJECT OBJECTID="165189947" OBJECTGUID="754629f6-7a31-46ea-9255-e772b3860492" CHANGEID="600882714" ISACTIVE="1" LEVELID="10" CREATEDATE="2024-09-11" UPDATEDATE="2024-09-11" /><OBJECT OBJECTID="165190623" OBJECTGUID="515f6163-f94f-42e0-8cad-9f5bb0673f3e" CHANGEID="600883806" ISACTIVE="1" LEVELID="9" CREATEDATE="2024-09-11" UPDATEDATE="2024-09-11" /><OBJECT OBJECTID="165191406" OBJECTGUID="dd657fa6-ea8a-4c53-b83f-6e7469f81d58" CHANGEID="600884909" ISACTIVE="1" LEVELID="10" CREATEDATE="2024-09-11" UPDATEDATE="2024-09-11" /><OBJECT OBJECTID="165191413" OBJECTGUID="890f9451-b383-4959-93c6-0fa3281190ac" CHANGEID="600884918" ISACTIVE="1" LEVELID="10" CREATEDATE="2024-09-11" UPDATEDATE="2024-09-11" /><OBJECT OBJECTID="165191403" OBJECTGUID="5dc74ef7-8079-40f1-869d-0928feca4520" CHANGEID="600884904" ISACTIVE="1" LEVELID="9" CREATEDATE="2024-09-11" UPDATEDATE="2024-09-11" /><OBJECT OBJECTID="165191415" OBJECTGUID="11b2e20c-e66f-4a5d-9d5f-5b60a4e17ce6" CHANGEID="600884923" ISACTIVE="1" LEVELID="10" CREATEDATE="2024-09-11" UPDATEDATE="2024-09-11" /><OBJECT OBJECTID="165191416" OBJECTGUID="a1616057-430c-44d9-aa39-16a5ae29738b" CHANGEID="600884925" ISACTIVE="1" LEVELID="10" CREATEDATE="2024-09-11" UPDATEDATE="2024-09-11" /><OBJECT OBJECTID="165191418" OBJECTGUID="07fa2d6b-7a3f-40e2-9db4-2c1c88dd3df4" CHANGEID="600884931" ISACTIVE="1" LEVELID="9" CREATEDATE="2024-09-11" UPDATEDATE="2024-09-11" /><OBJECT OBJECTID="165191419" OBJECTGUID="c5eba4e7-05d6-4db4-afb0-855ae01deac0" CHANGEID="600884933" ISACTIVE="1" LEVELID="10" CREATEDATE="2024-09-11" UPDATEDATE="2024-09-11" /><OBJECT OBJECTID="165192716" OBJECTGUID="1237b0f9-a80e-485a-81a4-24f5995d4639" CHANGEID="600886624" ISACTIVE="1" LEVELID="9" CREATEDATE="2024-09-11" UPDATEDATE="2024-09-11" /><OBJECT OBJECTID="165192715" OBJECTGUID="d5420a36-ba35-4b85-97ab-2c23c183e109" CHANGEID="600886623" ISACTIVE="1" LEVELID="9" CREATEDATE="2024-09-11" UPDATEDATE="2024-09-11" /><OBJECT OBJECTID="165192720" OBJECTGUID="dd4ecf9c-a876-410a-b9d0-c5169e4d4539" CHANGEID="600886633" ISACTIVE="1" LEVELID="9" CREATEDATE="2024-09-11" UPDATEDATE="2024-09-11" /><OBJECT OBJECTID="163088850" OBJECTGUID="241e0afe-bf3d-4f8a-9555-fcaebc7f0eb8" CHANGEID="600889843" ISACTIVE="1" LEVELID="9" CREATEDATE="2024-04-05" UPDATEDATE="2024-09-11" /><OBJECT OBJECTID="42913682" OBJECTGUID="35ce0c14-1f46-4ce6-b536-a93967d09629" CHANGEID="600898354" ISACTIVE="1" LEVELID="10" CREATEDATE="2019-07-10" UPDATEDATE="2024-09-11" /><OBJECT OBJECTID="165201042" OBJECTGUID="1a45e379-46ea-4b13-a93b-eb6533173778" CHANGEID="600898366" ISACTIVE="1" LEVELID="9" CREATEDATE="2024-09-11" UPDATEDATE="2024-09-11" /><OBJECT OBJECTID="72911478" OBJECTGUID="f4692760-a602-4e95-9fca-abfa989aabcf" CHANGEID="600898390" ISACTIVE="0" LEVELID="11" CREATEDATE="2018-08-08" UPDATEDATE="2024-09-11" /><OBJECT OBJECTID="72911446" OBJECTGUID="ad9826f4-d452-4951-bf21-391ac1bfbbe3" CHANGEID="600898392" ISACTIVE="0" LEVELID="11" CREATEDATE="2018-08-08" UPDATEDATE="2024-09-11" /><OBJECT OBJECTID="165201071" OBJECTGUID="bd360d59-fa5c-422c-a7ca-7bcffef94baf" CHANGEID="600898411" ISACTIVE="1" LEVELID="9" CREATEDATE="2024-09-11" UPDATEDATE="2024-09-11" /><OBJECT OBJECTID="73200955" OBJECTGUID="e4b4ee1c-393c-46e8-a52e-b22bb913b5cb" CHANGEID="600898350" ISACTIVE="0" LEVELID="11" CREATEDATE="2018-08-30" UPDATEDATE="2024-09-11" /><OBJECT OBJECTID="73200943" OBJECTGUID="0b94da5e-061f-4e4b-ae6d-8d96c2fa2d4b" CHANGEID="600898352" ISACTIVE="0" LEVELID="11" CREATEDATE="2018-08-30" UPDATEDATE="2024-09-11" /><OBJECT OBJECTID="165201033" OBJECTGUID="c5f80154-ff28-4e3b-b289-44d8d94f0f86" CHANGEID="600898357" ISACTIVE="1" LEVELID="9" CREATEDATE="2024-09-11" UPDATEDATE="2024-09-11" /><OBJECT OBJECTID="165201034" OBJECTGUID="749f025e-165f-4ed7-8719-9b8fe5e4daeb" CHANGEID="600898358" ISACTIVE="1" LEVELID="9" CREATEDATE="2024-09-11" UPDATEDATE="2024-09-11" /><OBJECT OBJECTID="165201035" OBJECTGUID="7485bc67-469c-4a4a-814b-8d2de3ee7977" CHANGEID="600898359" ISACTIVE="1" LEVELID="9" CREATEDATE="2024-09-11" UPDATEDATE="2024-09-11" /><OBJECT OBJECTID="165201036" OBJECTGUID="580dd439-a489-4c75-82f7-7601b288dd5c" CHANGEID="600898360" ISACTIVE="1" LEVELID="9" CREATEDATE="2024-09-11" UPDATEDATE="2024-09-11" /><OBJECT OBJECTID="165201037" OBJECTGUID="e0722244-44bf-4fd1-844a-77ba14e27b98" CHANGEID="600898361" ISACTIVE="1" LEVELID="9" CREATEDATE="2024-09-11" UPDATEDATE="2024-09-11" /><OBJECT OBJECTID="165201038" OBJECTGUID="2992a3e5-f2ab-4413-8eb0-8ff44777f15b" CHANGEID="600898362" ISACTIVE="1" LEVELID="9" CREATEDATE="2024-09-11" UPDATEDATE="2024-09-11" /><OBJECT OBJECTID="165201050" OBJECTGUID="0da2d8a0-3e62-489c-84c8-10514f7d79e8" CHANGEID="600898374" ISACTIVE="1" LEVELID="9" CREATEDATE="2024-09-11" UPDATEDATE="2024-09-11" /><OBJECT OBJECTID="165201069" OBJECTGUID="7de9eda7-1e2a-4b86-8bd1-d62bcc83a649" CHANGEID="600898405" ISACTIVE="1" LEVELID="9" CREATEDATE="2024-09-11" UPDATEDATE="2024-09-11" /><OBJECT OBJECTID="36306667" OBJECTGUID="1b314330-2b6c-48ce-b36e-bb59f08150ee" CHANGEID="600898409" ISACTIVE="0" LEVELID="11" CREATEDATE="2018-12-19" UPDATEDATE="2024-09-11" /><OBJECT OBJECTID="165201073" OBJECTGUID="1f625e21-69bc-4550-8c2a-8df4340649bf" CHANGEID="600898413" ISACTIVE="1" LEVELID="9" CREATEDATE="2024-09-11" UPDATEDATE="2024-09-11" /><OBJECT OBJECTID="165201123" OBJECTGUID="ab959d58-1a6a-490b-8371-6131296a9f6f" CHANGEID="600898466" ISACTIVE="1" LEVELID="9" CREATEDATE="2024-09-11" UPDATEDATE="2024-09-11" /><OBJECT OBJECTID="165202358" OBJECTGUID="1e33e738-58ec-47eb-9484-f4f69af885d0" CHANGEID="600899912" ISACTIVE="1" LEVELID="9" CREATEDATE="2024-09-11" UPDATEDATE="2024-09-11" /><OBJECT OBJECTID="165202373" OBJECTGUID="5f69c6cd-4ebb-448e-94db-60d2b671272e" CHANGEID="600899934" ISACTIVE="1" LEVELID="10" CREATEDATE="2024-09-11" UPDATEDATE="2024-09-11" /><OBJECT OBJECTID="165202375" OBJECTGUID="9410c3af-5aff-4bbe-986a-85518d746b4e" CHANGEID="600899936" ISACTIVE="1" LEVELID="9" CREATEDATE="2024-09-11" UPDATEDATE="2024-09-11" /><OBJECT OBJECTID="165202427" OBJECTGUID="d087b8a2-dea0-4278-8239-19174afd0739" CHANGEID="600899988" ISACTIVE="1" LEVELID="9" CREATEDATE="2024-09-11" UPDATEDATE="2024-09-11" /><OBJECT OBJECTID="165202374" OBJECTGUID="034f2748-cdf8-4148-943f-1d19b3ce1f7f" CHANGEID="600899935" ISACTIVE="1" LEVELID="10" CREATEDATE="2024-09-11" UPDATEDATE="2024-09-11" /><OBJECT OBJECTID="165202376" OBJECTGUID="373bf257-6b3c-457b-a8d3-4ba88d45b636" CHANGEID="600899937" ISACTIVE="1" LEVELID="9" CREATEDATE="2024-09-11" UPDATEDATE="2024-09-11" /><OBJECT OBJECTID="165202378" OBJECTGUID="2f03cce1-430b-40b1-be63-81282b2c5b46" CHANGEID="600899939" ISACTIVE="1" LEVELID="9" CREATEDATE="2024-09-11" UPDATEDATE="2024-09-11" /><OBJECT OBJECTID="165202780" OBJECTGUID="bcc0337a-b937-4f41-b0f3-e67a80231c41" CHANGEID="600900494" ISACTIVE="1" LEVELID="10" CREATEDATE="2024-09-11" UPDATEDATE="2024-09-11" /><OBJECT OBJECTID="42394519" OBJECTGUID="d120aeb8-e60b-4285-b60b-e34316afc4f6" CHANGEID="600901179" ISACTIVE="1" LEVELID="10" CREATEDATE="2019-07-10" UPDATEDATE="2024-09-11" /><OBJECT OBJECTID="165203367" OBJECTGUID="9fabad39-b180-4088-a662-15272cba939f" CHANGEID="600901213" ISACTIVE="1" LEVELID="9" CREATEDATE="2024-09-11" UPDATEDATE="2024-09-11" /><OBJECT OBJECTID="165203441" OBJECTGUID="93585102-5be1-446e-b3c4-e1b927da256e" CHANGEID="600901298" ISACTIVE="1" LEVELID="9" CREATEDATE="2024-09-11" UPDATEDATE="2024-09-11" /><OBJECT OBJECTID="165203461" OBJECTGUID="1aa8cddc-57a2-4dac-8147-d9b0ede4c794" CHANGEID="600901319" ISACTIVE="1" LEVELID="9" CREATEDATE="2024-09-11" UPDATEDATE="2024-09-11" /><OBJECT OBJECTID="165203462" OBJECTGUID="e4effa10-4767-41c0-bf1f-7b3bc8e35e2b" CHANGEID="600901320" ISACTIVE="1" LEVELID="9" CREATEDATE="2024-09-11" UPDATEDATE="2024-09-11" /><OBJECT OBJECTID="165204919" OBJECTGUID="7f4f4a29-90e7-4398-9021-aa9352b0a789" CHANGEID="600903662" ISACTIVE="1" LEVELID="10" CREATEDATE="2024-09-11" UPDATEDATE="2024-09-11" /><OBJECT OBJECTID="165207090" OBJECTGUID="1941440a-9767-4df8-875e-328325a72b0d" CHANGEID="600906881" ISACTIVE="1" LEVELID="10" CREATEDATE="2024-09-11" UPDATEDATE="2024-09-11" /><OBJECT OBJECTID="165207091" OBJECTGUID="1960fc0f-f406-46da-a3a3-b26a9a407cba" CHANGEID="600906882" ISACTIVE="1" LEVELID="10" CREATEDATE="2024-09-11" UPDATEDATE="2024-09-11" /><OBJECT OBJECTID="165207092" OBJECTGUID="05a643d0-2582-4f7a-94f0-a380b0ef03cd" CHANGEID="600906884" ISACTIVE="1" LEVELID="10" CREATEDATE="2024-09-11" UPDATEDATE="2024-09-11" /><OBJECT OBJECTID="165207093" OBJECTGUID="efaa3057-6b81-4696-acae-0d05d0c9a689" CHANGEID="600906885" ISACTIVE="1" LEVELID="10" CREATEDATE="2024-09-11" UPDATEDATE="2024-09-11" /><OBJECT OBJECTID="165207095" OBJECTGUID="61c629dd-7ea7-4536-8f6d-fd90b2fefce5" CHANGEID="600906887" ISACTIVE="1" LEVELID="10" CREATEDATE="2024-09-11" UPDATEDATE="2024-09-11" /><OBJECT OBJECTID="165207094" OBJECTGUID="5acfef6c-8d59-4f68-af0e-3bf13c28ba54" CHANGEID="600906886" ISACTIVE="1" LEVELID="9" CREATEDATE="2024-09-11" UPDATEDATE="2024-09-11" /><OBJECT OBJECTID="165207096" OBJECTGUID="4d8eac5d-1214-4637-a3e3-a34794e1bec5" CHANGEID="600906888" ISACTIVE="1" LEVELID="9" CREATEDATE="2024-09-11" UPDATEDATE="2024-09-11" /><OBJECT OBJECTID="165207102" OBJECTGUID="ce52d923-8ce5-43cc-a252-10cbbfcc15b6" CHANGEID="600906894" ISACTIVE="1" LEVELID="10" CREATEDATE="2024-09-11" UPDATEDATE="2024-09-11" /><OBJECT OBJECTID="165207129" OBJECTGUID="982285cb-c055-4400-b6ed-37630aa4d842" CHANGEID="600906921" ISACTIVE="1" LEVELID="7" CREATEDATE="2024-09-11" UPDATEDATE="2024-09-11" /><OBJECT OBJECTID="165207574" OBJECTGUID="87b076f1-0889-495b-9494-9ff308414aaa" CHANGEID="600907662" ISACTIVE="1" LEVELID="10" CREATEDATE="2024-09-11" UPDATEDATE="2024-09-11" /><OBJECT OBJECTID="165207685" OBJECTGUID="42e3380d-78da-4e2a-8cb5-9effbf00f5c6" CHANGEID="600907788" ISACTIVE="1" LEVELID="10" CREATEDATE="2024-09-11" UPDATEDATE="2024-09-11" /><OBJECT OBJECTID="27208134" OBJECTGUID="f3c2ae97-c153-4253-afcb-4095573f2f28" CHANGEID="600915405" ISACTIVE="1" LEVELID="11" CREATEDATE="2018-08-27" UPDATEDATE="2024-09-11" /><OBJECT OBJECTID="165212089" OBJECTGUID="3345f215-8e26-4bfd-8d92-6e124d626044" CHANGEID="600915675" ISACTIVE="1" LEVELID="9" CREATEDATE="2024-09-11" UPDATEDATE="2024-09-11" /><OBJECT OBJECTID="165215438" OBJECTGUID="c5d097f6-cd8a-4eb2-b8dc-6fa1f629d733" CHANGEID="600921395" ISACTIVE="1" LEVELID="10" CREATEDATE="2024-09-11" UPDATEDATE="2024-09-11" /><OBJECT OBJECTID="165215480" OBJECTGUID="6431596d-5723-45bb-85ae-5ef2361bba68" CHANGEID="600921467" ISACTIVE="1" LEVELID="10" CREATEDATE="2024-09-11" UPDATEDATE="2024-09-11" /><OBJECT OBJECTID="165215447" OBJECTGUID="bf0d00f4-415b-4405-a5c2-7ffac3841bca" CHANGEID="600921410" ISACTIVE="1" LEVELID="9" CREATEDATE="2024-09-11" UPDATEDATE="2024-09-11" /><OBJECT OBJECTID="165215487" OBJECTGUID="1840a28b-6f1a-49b0-a0fe-d3bca9603bde" CHANGEID="600921476" ISACTIVE="1" LEVELID="9" CREATEDATE="2024-09-11" UPDATEDATE="2024-09-11" /><OBJECT OBJECTID="165215524" OBJECTGUID="2188a076-c3e1-4f7c-a918-500e5b97c3e9" CHANGEID="600921533" ISACTIVE="1" LEVELID="10" CREATEDATE="2024-09-11" UPDATEDATE="2024-09-11" /><OBJECT OBJECTID="165215526" OBJECTGUID="1b687af5-0e54-47fc-8363-9d956ab4eeb6" CHANGEID="600921539" ISACTIVE="1" LEVELID="9" CREATEDATE="2024-09-11" UPDATEDATE="2024-09-11" /><OBJECT OBJECTID="165215506" OBJECTGUID="841b20ed-4aae-492a-80df-0fee2c1d0e07" CHANGEID="600921504" ISACTIVE="1" LEVELID="9" CREATEDATE="2024-09-11" UPDATEDATE="2024-09-11" /><OBJECT OBJECTID="165215809" OBJECTGUID="fef665d8-8de0-4712-8c6d-a3b6944552cc" CHANGEID="600922194" ISACTIVE="1" LEVELID="9" CREATEDATE="2024-09-11" UPDATEDATE="2024-09-11" /><OBJECT OBJECTID="165216427" OBJECTGUID="8b478189-a2c3-4672-ad19-f2c2583d9b2b" CHANGEID="600923144" ISACTIVE="1" LEVELID="10" CREATEDATE="2024-09-11" UPDATEDATE="2024-09-11" /><OBJECT OBJECTID="165216428" OBJECTGUID="697c60d2-6a30-45f2-b54d-95defd367aca" CHANGEID="600923145" ISACTIVE="1" LEVELID="10" CREATEDATE="2024-09-11" UPDATEDATE="2024-09-11" /><OBJECT OBJECTID="165217502" OBJECTGUID="5351a97f-dc97-4713-8581-8b4a70856715" CHANGEID="600924554" ISACTIVE="1" LEVELID="9" CREATEDATE="2024-09-11" UPDATEDATE="2024-09-11" /><OBJECT OBJECTID="165217510" OBJECTGUID="35c13b60-fb80-48e6-9d55-8c80b3fad963" CHANGEID="600924564" ISACTIVE="1" LEVELID="10" CREATEDATE="2024-09-11" UPDATEDATE="2024-09-11" /><OBJECT OBJECTID="165223076" OBJECTGUID="1a1d9b40-9bdc-4301-a299-4a58a50d7d9d" CHANGEID="600934843" ISACTIVE="1" LEVELID="10" CREATEDATE="2024-09-12" UPDATEDATE="2024-09-12" /><OBJECT OBJECTID="73228327" OBJECTGUID="b3bdc164-ca40-4dbe-93ae-59bad6d4d4de" CHANGEID="600935329" ISACTIVE="1" LEVELID="10" CREATEDATE="2019-07-10" UPDATEDATE="2024-09-12" /><OBJECT OBJECTID="165223484" OBJECTGUID="5b1be562-3988-4394-a296-ce509be7f934" CHANGEID="600935328" ISACTIVE="1" LEVELID="11" CREATEDATE="2024-09-12" UPDATEDATE="2024-09-12" /><OBJECT OBJECTID="165224040" OBJECTGUID="4cbe032c-a46d-4f4f-a0f4-483c03ab58d1" CHANGEID="600936019" ISACTIVE="1" LEVELID="9" CREATEDATE="2024-09-12" UPDATEDATE="2024-09-12" /><OBJECT OBJECTID="96552058" OBJECTGUID="d22b02f2-c83b-4b15-805c-e209eaa9a999" CHANGEID="600936020" ISACTIVE="1" LEVELID="9" CREATEDATE="2020-04-29" UPDATEDATE="2024-09-12" /><OBJECT OBJECTID="165224133" OBJECTGUID="12d2c38a-0eb6-4a5f-be01-e64dd9ae9879" CHANGEID="600936132" ISACTIVE="1" LEVELID="10" CREATEDATE="2024-09-12" UPDATEDATE="2024-09-12" /><OBJECT OBJECTID="165224492" OBJECTGUID="cedf4881-460c-46fd-bf9d-9ae16c8bdf6e" CHANGEID="600936671" ISACTIVE="1" LEVELID="9" CREATEDATE="2024-09-12" UPDATEDATE="2024-09-12" /><OBJECT OBJECTID="165224511" OBJECTGUID="f2093fdd-0c9a-4a24-909c-c1d9b93ed0c6" CHANGEID="600936770" ISACTIVE="1" LEVELID="9" CREATEDATE="2024-09-12" UPDATEDATE="2024-09-12" /><OBJECT OBJECTID="165224513" OBJECTGUID="24fdde58-0f92-4554-a046-7edb2fdd3876" CHANGEID="600936772" ISACTIVE="1" LEVELID="9" CREATEDATE="2024-09-12" UPDATEDATE="2024-09-12" /><OBJECT OBJECTID="165224514" OBJECTGUID="dc9a4535-43b3-40ad-85e4-947bc4a2ed6a" CHANGEID="600936780" ISACTIVE="1" LEVELID="10" CREATEDATE="2024-09-12" UPDATEDATE="2024-09-12" /><OBJECT OBJECTID="165224510" OBJECTGUID="36b19160-5257-4377-8762-33708fc0d1f8" CHANGEID="600936767" ISACTIVE="1" LEVELID="10" CREATEDATE="2024-09-12" UPDATEDATE="2024-09-12" /><OBJECT OBJECTID="165224512" OBJECTGUID="27138806-33f0-4655-9061-c4f8cdbd7ab7" CHANGEID="600936771" ISACTIVE="1" LEVELID="10" CREATEDATE="2024-09-12" UPDATEDATE="2024-09-12" /><OBJECT OBJECTID="72910621" OBJECTGUID="a10b3d6d-9ce4-4206-8af4-4a31b766c879" CHANGEID="600936779" ISACTIVE="0" LEVELID="10" CREATEDATE="2017-04-04" UPDATEDATE="2024-09-12" /><OBJECT OBJECTID="165225733" OBJECTGUID="5cc2e293-edb0-4f81-be9a-117917369bd8" CHANGEID="600938548" ISACTIVE="1" LEVELID="9" CREATEDATE="2024-09-12" UPDATEDATE="2024-09-12" /><OBJECT OBJECTID="165225734" OBJECTGUID="398a7073-3d29-4bc3-95e2-2af198adeffb" CHANGEID="600938549" ISACTIVE="1" LEVELID="9" CREATEDATE="2024-09-12" UPDATEDATE="2024-09-12" /><OBJECT OBJECTID="28945051" OBJECTGUID="4a6032d5-1660-41cf-b933-b3c28a92ddb6" CHANGEID="600939815" ISACTIVE="1" LEVELID="10" CREATEDATE="2019-01-24" UPDATEDATE="2024-09-12" /><OBJECT OBJECTID="71656982" OBJECTGUID="8512ec90-9f05-43e1-8468-4f120922f6dd" CHANGEID="600942681" ISACTIVE="1" LEVELID="10" CREATEDATE="2017-12-18" UPDATEDATE="2024-09-12" /><OBJECT OBJECTID="165228728" OBJECTGUID="69d138b0-3ddf-4edc-81fb-39e5c61f4d71" CHANGEID="600942940" ISACTIVE="1" LEVELID="10" CREATEDATE="2024-09-12" UPDATEDATE="2024-09-12" /><OBJECT OBJECTID="165231589" OBJECTGUID="26d5182d-aa84-44bc-920a-d1a081ec133c" CHANGEID="600947023" ISACTIVE="1" LEVELID="10" CREATEDATE="2024-09-12" UPDATEDATE="2024-09-12" /><OBJECT OBJECTID="165231590" OBJECTGUID="4c4e5425-18b8-4199-924a-4806c3b3f6dc" CHANGEID="600947027" ISACTIVE="1" LEVELID="9" CREATEDATE="2024-09-12" UPDATEDATE="2024-09-12" /><OBJECT OBJECTID="165232286" OBJECTGUID="1d4fa7d5-e630-49cc-89c8-8ff1698dd374" CHANGEID="600947902" ISACTIVE="1" LEVELID="8" CREATEDATE="2024-09-12" UPDATEDATE="2024-09-12" /><OBJECT OBJECTID="165232287" OBJECTGUID="2b4862c3-1d88-4375-b892-9c053d92231c" CHANGEID="600947903" ISACTIVE="1" LEVELID="8" CREATEDATE="2024-09-12" UPDATEDATE="2024-09-12" /><OBJECT OBJECTID="165232288" OBJECTGUID="2864fd9e-5a79-4d9c-a7f3-6ca176f1361a" CHANGEID="600947904" ISACTIVE="1" LEVELID="8" CREATEDATE="2024-09-12" UPDATEDATE="2024-09-12" /><OBJECT OBJECTID="165239335" OBJECTGUID="b92f80bf-ad6b-491b-9849-d7e75b98aeea" CHANGEID="600957720" ISACTIVE="1" LEVELID="10" CREATEDATE="2024-09-12" UPDATEDATE="2024-09-12" /><OBJECT OBJECTID="165239354" OBJECTGUID="928778f4-b7a5-41c6-b491-d3afa86b6b45" CHANGEID="600957742" ISACTIVE="1" LEVELID="9" CREATEDATE="2024-09-12" UPDATEDATE="2024-09-12" /><OBJECT OBJECTID="59306221" OBJECTGUID="0b946075-de8c-4a90-a809-8484dba6cf61" CHANGEID="600961609" ISACTIVE="1" LEVELID="11" CREATEDATE="2019-07-19" UPDATEDATE="2024-09-12" /><OBJECT OBJECTID="165242047" OBJECTGUID="cb99b411-c4a7-4c05-a773-db130ab8ca6f" CHANGEID="600961801" ISACTIVE="1" LEVELID="10" CREATEDATE="2024-09-12" UPDATEDATE="2024-09-12" /><OBJECT OBJECTID="165242049" OBJECTGUID="40b33449-964f-4d2f-b274-86a747826f9f" CHANGEID="600961803" ISACTIVE="1" LEVELID="9" CREATEDATE="2024-09-12" UPDATEDATE="2024-09-12" /><OBJECT OBJECTID="165243296" OBJECTGUID="52ec3757-efef-408a-a14a-12e36873fd2c" CHANGEID="600963412" ISACTIVE="1" LEVELID="9" CREATEDATE="2024-09-12" UPDATEDATE="2024-09-12" /><OBJECT OBJECTID="165243318" OBJECTGUID="1f25db84-5f6f-4288-a30b-26bf81ba0a5b" CHANGEID="600963437" ISACTIVE="1" LEVELID="9" CREATEDATE="2024-09-12" UPDATEDATE="2024-09-12" /><OBJECT OBJECTID="165243325" OBJECTGUID="690e8b5f-9a67-44f5-bea5-ff933fa37d55" CHANGEID="600963446" ISACTIVE="1" LEVELID="10" CREATEDATE="2024-09-12" UPDATEDATE="2024-09-12" /><OBJECT OBJECTID="165243334" OBJECTGUID="643bac65-6f70-4476-806f-6f8dfbff0505" CHANGEID="600963456" ISACTIVE="1" LEVELID="9" CREATEDATE="2024-09-12" UPDATEDATE="2024-09-12" /><OBJECT OBJECTID="165243337" OBJECTGUID="eefe6d9b-0cd4-4278-a5aa-cb3fee7cefca" CHANGEID="600963460" ISACTIVE="1" LEVELID="10" CREATEDATE="2024-09-12" UPDATEDATE="2024-09-12" /><OBJECT OBJECTID="165243345" OBJECTGUID="ec351e96-4bc0-4d8f-8bc8-63c8796e58c6" CHANGEID="600963469" ISACTIVE="1" LEVELID="9" CREATEDATE="2024-09-12" UPDATEDATE="2024-09-12" /><OBJECT OBJECTID="165243346" OBJECTGUID="52f29993-bf0c-493f-bffc-a078daa7c19f" CHANGEID="600963470" ISACTIVE="1" LEVELID="9" CREATEDATE="2024-09-12" UPDATEDATE="2024-09-12" /><OBJECT OBJECTID="165243936" OBJECTGUID="0b412d47-e359-481a-aaae-ff2f3c68f026" CHANGEID="600964400" ISACTIVE="1" LEVELID="9" CREATEDATE="2024-09-12" UPDATEDATE="2024-09-12" /><OBJECT OBJECTID="165245873" OBJECTGUID="4d945713-2dcd-4d39-b767-7be8b4e8a159" CHANGEID="600967357" ISACTIVE="1" LEVELID="9" CREATEDATE="2024-09-12" UPDATEDATE="2024-09-12" /><OBJECT OBJECTID="165250599" OBJECTGUID="7c97923b-6871-4b54-9b61-7164fbfcc6e8" CHANGEID="600974753" ISACTIVE="1" LEVELID="9" CREATEDATE="2024-09-12" UPDATEDATE="2024-09-12" /><OBJECT OBJECTID="165251726" OBJECTGUID="fc242dec-4dde-4675-9002-99deb666c8e1" CHANGEID="600976879" ISACTIVE="1" LEVELID="9" CREATEDATE="2024-09-12" UPDATEDATE="2024-09-12" /><OBJECT OBJECTID="32225351" OBJECTGUID="afeeb9d1-c6a0-4298-a5e1-3b165005c71d" CHANGEID="600797437" ISACTIVE="1" LEVELID="11" CREATEDATE="2017-04-25" UPDATEDATE="2024-09-10" /><OBJECT OBJECTID="36307034" OBJECTGUID="a05fcff7-bcb4-4531-a117-70a4c9aede8b" CHANGEID="600898407" ISACTIVE="0" LEVELID="11" CREATEDATE="2018-12-19" UPDATEDATE="2024-09-11" /><OBJECT OBJECTID="46009914" OBJECTGUID="f0ad373d-a1dd-477d-a91d-2445d167b651" CHANGEID="600737845" ISACTIVE="0" LEVELID="11" CREATEDATE="2017-05-15" UPDATEDATE="2024-09-09" /><OBJECT OBJECTID="15364103" OBJECTGUID="7d090ca6-90b4-49fe-90b3-6ba0e2e9d7f6" CHANGEID="600798225" ISACTIVE="1" LEVELID="10" CREATEDATE="2019-07-10" UPDATEDATE="2024-09-10" /><OBJECT OBJECTID="164754161" OBJECTGUID="175f9564-c514-4730-be00-b37e5b960078" CHANGEID="600880433" ISACTIVE="1" LEVELID="10" CREATEDATE="2024-08-19" UPDATEDATE="2024-09-11" /><OBJECT OBJECTID="60813648" OBJECTGUID="989d61c1-4e5f-4468-97b1-d5cde1ea1536" CHANGEID="600901226" ISACTIVE="1" LEVELID="11" CREATEDATE="2018-08-28" UPDATEDATE="2024-09-11" /><OBJECT OBJECTID="98197092" OBJECTGUID="925cf97c-36c9-4f0c-9309-451c13eb7cc3" CHANGEID="600901232" ISACTIVE="1" LEVELID="10" CREATEDATE="2020-09-08" UPDATEDATE="2024-09-11" /><OBJECT OBJECTID="46009524" OBJECTGUID="2c3ebfa5-02ef-435c-8a7d-2faad95b88b4" CHANGEID="600737846" ISACTIVE="0" LEVELID="11" CREATEDATE="2017-05-15" UPDATEDATE="2024-09-09" /><OBJECT OBJECTID="58686338" OBJECTGUID="6ba48486-4943-4f45-b065-a982dc927052" CHANGEID="600798217" ISACTIVE="0" LEVELID="11" CREATEDATE="2018-08-16" UPDATEDATE="2024-09-10" /><OBJECT OBJECTID="164827569" OBJECTGUID="65713d15-ee17-4caf-ba4c-91d224f20219" CHANGEID="600763194" ISACTIVE="0" LEVELID="9" CREATEDATE="2024-08-22" UPDATEDATE="2024-09-09" /><OBJECT OBJECTID="164827648" OBJECTGUID="53981d34-4e34-4fc8-8572-c8e3cdfd4167" CHANGEID="600860111" ISACTIVE="1" LEVELID="10" CREATEDATE="2024-08-22" UPDATEDATE="2024-09-11" /><OBJECT OBJECTID="78675358" OBJECTGUID="8e0e525b-abdc-4e30-80f7-ca8eb68c7ed8" CHANGEID="600902691" ISACTIVE="1" LEVELID="11" CREATEDATE="2019-07-19" UPDATEDATE="2024-09-11" /><OBJECT OBJECTID="164845553" OBJECTGUID="57ac0df3-aad8-4691-891f-4f6c9c360f05" CHANGEID="600742198" ISACTIVE="1" LEVELID="9" CREATEDATE="2024-08-23" UPDATEDATE="2024-09-09" /><OBJECT OBJECTID="164845552" OBJECTGUID="3e8e5cbc-0ba8-44b0-8538-2b37de2404d5" CHANGEID="600819372" ISACTIVE="1" LEVELID="9" CREATEDATE="2024-08-23" UPDATEDATE="2024-09-10" /><OBJECT OBJECTID="164033107" OBJECTGUID="1d7d3f6e-712a-4f25-8210-98de7ae40213" CHANGEID="600859909" ISACTIVE="1" LEVELID="10" CREATEDATE="2024-06-27" UPDATEDATE="2024-09-11" /><OBJECT OBJECTID="164885475" OBJECTGUID="4f4bee5b-59b2-4081-b0b2-f01dea285071" CHANGEID="600860098" ISACTIVE="1" LEVELID="10" CREATEDATE="2024-08-27" UPDATEDATE="2024-09-11" /><OBJECT OBJECTID="79284046" OBJECTGUID="bfd79093-d172-4adb-99ad-3f1f92f4860d" CHANGEID="600830196" ISACTIVE="0" LEVELID="11" CREATEDATE="2018-08-27" UPDATEDATE="2024-09-10" /><OBJECT OBJECTID="164654770" OBJECTGUID="aa0f9cd7-3416-46e5-af9b-12615aef594d" CHANGEID="600859999" ISACTIVE="1" LEVELID="10" CREATEDATE="2024-08-13" UPDATEDATE="2024-09-11" /><OBJECT OBJECTID="93239974" OBJECTGUID="14bcc72c-b515-4762-9107-c7072d50cedd" CHANGEID="600936021" ISACTIVE="1" LEVELID="9" CREATEDATE="2019-12-27" UPDATEDATE="2024-09-12" /><OBJECT OBJECTID="41434120" OBJECTGUID="026aa5a7-33f9-40c1-8ae8-5346de11e5ab" CHANGEID="600749666" ISACTIVE="0" LEVELID="11" CREATEDATE="2019-03-12" UPDATEDATE="2024-09-09" /><OBJECT OBJECTID="164935245" OBJECTGUID="fed62620-a9f6-4674-a756-f87d8ba7f4e9" CHANGEID="600860096" ISACTIVE="1" LEVELID="10" CREATEDATE="2024-08-29" UPDATEDATE="2024-09-11" /><OBJECT OBJECTID="103107845" OBJECTGUID="a115b922-d129-4c51-acec-20d1238b89f5" CHANGEID="600798222" ISACTIVE="1" LEVELID="9" CREATEDATE="2021-12-03" UPDATEDATE="2024-09-10" /><OBJECT OBJECTID="16898211" OBJECTGUID="166efff7-bb8a-4905-adb8-04914cc4fcc7" CHANGEID="600798227" ISACTIVE="1" LEVELID="11" CREATEDATE="2017-05-04" UPDATEDATE="2024-09-10" /><OBJECT OBJECTID="17365457" OBJECTGUID="ce28fa6a-b119-4c43-8eca-c9373701d5b0" CHANGEID="600779412" ISACTIVE="1" LEVELID="11" CREATEDATE="2017-05-11" UPDATEDATE="2024-09-09" /><OBJECT OBJECTID="103107841" OBJECTGUID="44119e54-0976-47b6-803b-cb949e4277ef" CHANGEID="600798220" ISACTIVE="1" LEVELID="9" CREATEDATE="2021-12-03" UPDATEDATE="2024-09-10" /><OBJECT OBJECTID="72303679" OBJECTGUID="d062fb02-6bbd-4561-a57e-4ffde18e246d" CHANGEID="600742190" ISACTIVE="1" LEVELID="10" CREATEDATE="2019-01-22" UPDATEDATE="2024-09-09" /></REESTR_OBJECTS>