<?xml version="1.0" encoding="utf-8"?><APARTMENTS><APARTMENT ID="108526376" OBJECTID="100095808" OBJECTGUID="d267f758-4f50-4b96-b5d2-763017b83826" CHANGEID="600752481" NUMBER="1" APARTTYPE="2" OPERTYPEID="30" PREVID="52286295" NEXTID="0" UPDATEDATE="2024-09-09" STARTDATE="2024-09-09" ENDDATE="2079-06-06" ISACTUAL="1" ISACTIVE="0" /><APARTMENT ID="52286295" OBJECTID="100095808" OBJECTGUID="d267f758-4f50-4b96-b5d2-763017b83826" CHANGEID="171505627" NUMBER="1" APARTTYPE="2" OPERTYPEID="10" PREVID="0" NEXTID="108526376" UPDATEDATE="2024-09-09" STARTDATE="2021-01-27" ENDDATE="2024-09-09" ISACTUAL="0" ISACTIVE="0" /><APARTMENT ID="108526377" OBJECTID="100095807" OBJECTGUID="239013f5-9710-4e68-bfbe-80c82838bff4" CHANGEID="600752482" NUMBER="2" APARTTYPE="2" OPERTYPEID="30" PREVID="52286294" NEXTID="0" UPDATEDATE="2024-09-09" STARTDATE="2024-09-09" ENDDATE="2079-06-06" ISACTUAL="1" ISACTIVE="0" /><APARTMENT ID="52286294" OBJECTID="100095807" OBJECTGUID="239013f5-9710-4e68-bfbe-80c82838bff4" CHANGEID="171505626" NUMBER="2" APARTTYPE="2" OPERTYPEID="10" PREVID="0" NEXTID="108526377" UPDATEDATE="2024-09-09" STARTDATE="2021-01-27" ENDDATE="2024-09-09" ISACTUAL="0" ISACTIVE="0" /><APARTMENT ID="108526378" OBJECTID="165126463" OBJECTGUID="f4edf8ac-72e1-49d4-bb78-4eb24e59fd4a" CHANGEID="600752483" NUMBER="2" APARTTYPE="2" OPERTYPEID="10" PREVID="0" NEXTID="0" UPDATEDATE="2024-09-09" STARTDATE="2024-09-09" ENDDATE="2079-06-06" ISACTUAL="1" ISACTIVE="1" /><APARTMENT ID="108526379" OBJECTID="165126468" OBJECTGUID="0687d71b-2768-4188-9018-d0c0bb883fc9" CHANGEID="600752488" NUMBER="3" APARTTYPE="2" OPERTYPEID="10" PREVID="0" NEXTID="0" UPDATEDATE="2024-09-09" STARTDATE="2024-09-09" ENDDATE="2079-06-06" ISACTUAL="1" ISACTIVE="1" /><APARTMENT ID="108526380" OBJECTID="165126470" OBJECTGUID="353022d7-bd15-4ab5-95fa-d4c4e466a1c1" CHANGEID="600752490" NUMBER="6" APARTTYPE="2" OPERTYPEID="10" PREVID="0" NEXTID="0" UPDATEDATE="2024-09-09" STARTDATE="2024-09-09" ENDDATE="2079-06-06" ISACTUAL="1" ISACTIVE="1" /><APARTMENT ID="108526381" OBJECTID="165126471" OBJECTGUID="13a5f5a4-911b-46ee-b503-8ebc53450492" CHANGEID="600752495" NUMBER="1" APARTTYPE="2" OPERTYPEID="10" PREVID="0" NEXTID="0" UPDATEDATE="2024-09-09" STARTDATE="2024-09-09" ENDDATE="2079-06-06" ISACTUAL="1" ISACTIVE="1" /><APARTMENT ID="108526382" OBJECTID="165126472" OBJECTGUID="efac4b11-19c4-45ec-8a12-873786ead442" CHANGEID="600752496" NUMBER="2" APARTTYPE="2" OPERTYPEID="10" PREVID="0" NEXTID="0" UPDATEDATE="2024-09-09" STARTDATE="2024-09-09" ENDDATE="2079-06-06" ISACTUAL="1" ISACTIVE="1" /><APARTMENT ID="108526383" OBJECTID="165126473" OBJECTGUID="0aa1c638-cca7-4d9e-bcb0-588f287911b2" CHANGEID="600752497" NUMBER="1" APARTTYPE="2" OPERTYPEID="10" PREVID="0" NEXTID="0" UPDATEDATE="2024-09-09" STARTDATE="2024-09-09" ENDDATE="2079-06-06" ISACTUAL="1" ISACTIVE="1" /><APARTMENT ID="108526384" OBJECTID="165126474" OBJECTGUID="0da36b5a-636e-42f9-980e-ad389d305512" CHANGEID="600752498" NUMBER="1" APARTTYPE="2" OPERTYPEID="10" PREVID="0" NEXTID="0" UPDATEDATE="2024-09-09" STARTDATE="2024-09-09" ENDDATE="2079-06-06" ISACTUAL="1" ISACTIVE="1" /><APARTMENT ID="108526385" OBJECTID="165126475" OBJECTGUID="48dd727d-4242-4659-beb7-76d4509b3296" CHANGEID="600752499" NUMBER="1001" APARTTYPE="1" OPERTYPEID="10" PREVID="0" NEXTID="0" UPDATEDATE="2024-09-09" STARTDATE="2024-09-09" ENDDATE="2079-06-06" ISACTUAL="1" ISACTIVE="1" /><APARTMENT ID="108526388" OBJECTID="165126495" OBJECTGUID="5c732adb-2163-4812-90ac-0bc354c99616" CHANGEID="600752534" NUMBER="12" APARTTYPE="2" OPERTYPEID="10" PREVID="0" NEXTID="0" UPDATEDATE="2024-09-09" STARTDATE="2024-09-09" ENDDATE="2079-06-06" ISACTUAL="1" ISACTIVE="1" /><APARTMENT ID="108526389" OBJECTID="165126499" OBJECTGUID="3f1970fd-83ac-4096-8c8e-92e039aa6938" CHANGEID="600752539" NUMBER="10" APARTTYPE="2" OPERTYPEID="10" PREVID="0" NEXTID="0" UPDATEDATE="2024-09-09" STARTDATE="2024-09-09" ENDDATE="2079-06-06" ISACTUAL="1" ISACTIVE="1" /><APARTMENT ID="108526390" OBJECTID="165126504" OBJECTGUID="b80b38c1-1dda-4eec-962d-16969c33b04c" CHANGEID="600752544" NUMBER="1" APARTTYPE="2" OPERTYPEID="10" PREVID="0" NEXTID="0" UPDATEDATE="2024-09-09" STARTDATE="2024-09-09" ENDDATE="2079-06-06" ISACTUAL="1" ISACTIVE="1" /><APARTMENT ID="108526652" OBJECTID="165127959" OBJECTGUID="73050f49-4292-4e2c-935b-56aff83fc85f" CHANGEID="600755346" NUMBER="72" APARTTYPE="2" OPERTYPEID="10" PREVID="0" NEXTID="0" UPDATEDATE="2024-09-09" STARTDATE="2024-09-09" ENDDATE="2079-06-06" ISACTUAL="1" ISACTIVE="1" /><APARTMENT ID="108526651" OBJECTID="165127954" OBJECTGUID="eaa46ca7-cbe4-4936-ac0c-7b29a6df80ac" CHANGEID="600755337" NUMBER="2" APARTTYPE="2" OPERTYPEID="10" PREVID="0" NEXTID="0" UPDATEDATE="2024-09-09" STARTDATE="2024-09-09" ENDDATE="2079-06-06" ISACTUAL="1" ISACTIVE="1" /><APARTMENT ID="108532821" OBJECTID="165141469" OBJECTGUID="79bc9a8b-855f-473f-9275-e32adb4f698d" CHANGEID="600776561" NUMBER="1" APARTTYPE="2" OPERTYPEID="10" PREVID="0" NEXTID="0" UPDATEDATE="2024-09-09" STARTDATE="2024-09-09" ENDDATE="2079-06-06" ISACTUAL="1" ISACTIVE="1" /><APARTMENT ID="108533258" OBJECTID="165142826" OBJECTGUID="72086eb5-ba91-495c-b27e-26255a842fdf" CHANGEID="600779690" NUMBER="2" APARTTYPE="2" OPERTYPEID="10" PREVID="0" NEXTID="0" UPDATEDATE="2024-09-09" STARTDATE="2024-09-09" ENDDATE="2079-06-06" ISACTUAL="1" ISACTIVE="1" /><APARTMENT ID="108541577" OBJECTID="165161357" OBJECTGUID="7c9f6682-1e98-4d8e-b4b6-3ded23d0cdc4" CHANGEID="600812997" NUMBER="1004" APARTTYPE="1" OPERTYPEID="10" PREVID="0" NEXTID="0" UPDATEDATE="2024-09-10" STARTDATE="2024-09-10" ENDDATE="2079-06-06" ISACTUAL="1" ISACTIVE="1" /><APARTMENT ID="108541578" OBJECTID="165161360" OBJECTGUID="0da7dd47-8f07-4022-b2ed-7e1315725bfc" CHANGEID="600813001" NUMBER="1005" APARTTYPE="1" OPERTYPEID="10" PREVID="0" NEXTID="0" UPDATEDATE="2024-09-10" STARTDATE="2024-09-10" ENDDATE="2079-06-06" ISACTUAL="1" ISACTIVE="1" /><APARTMENT ID="108541579" OBJECTID="3705367" OBJECTGUID="5e2d54ae-9464-4cbb-816e-ad81ab47376f" CHANGEID="600813043" NUMBER="1002" APARTTYPE="1" OPERTYPEID="20" PREVID="1383091" UPDATEDATE="2024-09-10" STARTDATE="2024-09-10" ENDDATE="2079-06-06" ISACTUAL="1" ISACTIVE="1" /><APARTMENT ID="1383091" OBJECTID="3705367" OBJECTGUID="5e2d54ae-9464-4cbb-816e-ad81ab47376f" CHANGEID="7305516" NUMBER="6" APARTTYPE="2" OPERTYPEID="10" PREVID="0" NEXTID="108541579" UPDATEDATE="2024-09-10" STARTDATE="2018-12-06" ENDDATE="2024-09-10" ISACTUAL="0" ISACTIVE="0" /><APARTMENT ID="108547265" OBJECTID="165179527" OBJECTGUID="58bab938-afaf-4699-86f7-1cc625ec48a2" CHANGEID="600841662" NUMBER="3" APARTTYPE="2" OPERTYPEID="10" PREVID="0" NEXTID="0" UPDATEDATE="2024-09-10" STARTDATE="2024-09-10" ENDDATE="2079-06-06" ISACTUAL="1" ISACTIVE="1" /><APARTMENT ID="108547285" OBJECTID="165179563" OBJECTGUID="aa621b84-dace-40b3-ba7d-b2556659ce8e" CHANGEID="600841728" NUMBER="3" APARTTYPE="2" OPERTYPEID="10" PREVID="0" NEXTID="0" UPDATEDATE="2024-09-10" STARTDATE="2024-09-10" ENDDATE="2079-06-06" ISACTUAL="1" ISACTIVE="1" /><APARTMENT ID="108547320" OBJECTID="165179638" OBJECTGUID="86981903-c3b4-4eca-bb82-23d03b82eece" CHANGEID="600841879" NUMBER="2" APARTTYPE="2" OPERTYPEID="10" PREVID="0" NEXTID="0" UPDATEDATE="2024-09-10" STARTDATE="2024-09-10" ENDDATE="2079-06-06" ISACTUAL="1" ISACTIVE="1" /><APARTMENT ID="108547324" OBJECTID="165179644" OBJECTGUID="cac0327d-c223-4cf1-9291-75a82ecc7e1e" CHANGEID="600841905" NUMBER="3" APARTTYPE="2" OPERTYPEID="10" PREVID="0" NEXTID="0" UPDATEDATE="2024-09-10" STARTDATE="2024-09-10" ENDDATE="2079-06-06" ISACTUAL="1" ISACTIVE="1" /><APARTMENT ID="108547281" OBJECTID="165179554" OBJECTGUID="952c5a65-9565-4995-8a03-510868790bc5" CHANGEID="600841711" NUMBER="2" APARTTYPE="2" OPERTYPEID="10" PREVID="0" NEXTID="0" UPDATEDATE="2024-09-10" STARTDATE="2024-09-10" ENDDATE="2079-06-06" ISACTUAL="1" ISACTIVE="1" /><APARTMENT ID="108547295" OBJECTID="165179575" OBJECTGUID="689e67c8-5c9c-4b62-a654-167518799245" CHANGEID="600841751" NUMBER="2" APARTTYPE="2" OPERTYPEID="10" PREVID="0" NEXTID="0" UPDATEDATE="2024-09-10" STARTDATE="2024-09-10" ENDDATE="2079-06-06" ISACTUAL="1" ISACTIVE="1" /><APARTMENT ID="108547302" OBJECTID="165179582" OBJECTGUID="557f49d7-427b-4519-8f91-970e27ff1d9e" CHANGEID="600841769" NUMBER="4" APARTTYPE="2" OPERTYPEID="10" PREVID="0" NEXTID="0" UPDATEDATE="2024-09-10" STARTDATE="2024-09-10" ENDDATE="2079-06-06" ISACTUAL="1" ISACTIVE="1" /><APARTMENT ID="108547308" OBJECTID="165179596" OBJECTGUID="8f18c1cc-781e-4136-b451-c9a39349f4db" CHANGEID="600841801" NUMBER="4" APARTTYPE="2" OPERTYPEID="10" PREVID="0" NEXTID="0" UPDATEDATE="2024-09-10" STARTDATE="2024-09-10" ENDDATE="2079-06-06" ISACTUAL="1" ISACTIVE="1" /><APARTMENT ID="108547311" OBJECTID="165179610" OBJECTGUID="57263761-3e5a-4959-9de4-47cea28b2675" CHANGEID="600841833" NUMBER="3" APARTTYPE="2" OPERTYPEID="10" PREVID="0" NEXTID="0" UPDATEDATE="2024-09-10" STARTDATE="2024-09-10" ENDDATE="2079-06-06" ISACTUAL="1" ISACTIVE="1" /><APARTMENT ID="108547322" OBJECTID="165179641" OBJECTGUID="076a2169-2845-472f-9ba1-c78354dcf0f8" CHANGEID="600841894" NUMBER="16" APARTTYPE="2" OPERTYPEID="10" PREVID="0" NEXTID="0" UPDATEDATE="2024-09-10" STARTDATE="2024-09-10" ENDDATE="2079-06-06" ISACTUAL="1" ISACTIVE="1" /><APARTMENT ID="108547496" OBJECTID="165179989" OBJECTGUID="548eab50-c2c4-41e7-946c-cfa11e45129f" CHANGEID="600842571" NUMBER="5" APARTTYPE="2" OPERTYPEID="10" PREVID="0" NEXTID="0" UPDATEDATE="2024-09-10" STARTDATE="2024-09-10" ENDDATE="2079-06-06" ISACTUAL="1" ISACTIVE="1" /><APARTMENT ID="108547759" OBJECTID="165180404" OBJECTGUID="787e22bf-558a-415d-8b7a-8a81c05ffa25" CHANGEID="600843130" NUMBER="4" APARTTYPE="2" OPERTYPEID="10" PREVID="0" NEXTID="0" UPDATEDATE="2024-09-10" STARTDATE="2024-09-10" ENDDATE="2079-06-06" ISACTUAL="1" ISACTIVE="1" /><APARTMENT ID="108547776" OBJECTID="165180429" OBJECTGUID="d5b266cc-f59d-4a83-9762-1272634fab3f" CHANGEID="600843168" NUMBER="1" APARTTYPE="2" OPERTYPEID="10" PREVID="0" NEXTID="0" UPDATEDATE="2024-09-10" STARTDATE="2024-09-10" ENDDATE="2079-06-06" ISACTUAL="1" ISACTIVE="1" /><APARTMENT ID="108547890" OBJECTID="165180627" OBJECTGUID="af6cabb1-f341-4b3e-812e-e26a2cbf9c27" CHANGEID="600843567" NUMBER="1" APARTTYPE="2" OPERTYPEID="10" PREVID="0" NEXTID="0" UPDATEDATE="2024-09-10" STARTDATE="2024-09-10" ENDDATE="2079-06-06" ISACTUAL="1" ISACTIVE="1" /><APARTMENT ID="108547897" OBJECTID="165180646" OBJECTGUID="f0853916-ca86-40e2-8dea-489627d547f4" CHANGEID="600843610" NUMBER="4" APARTTYPE="2" OPERTYPEID="10" PREVID="0" NEXTID="0" UPDATEDATE="2024-09-10" STARTDATE="2024-09-10" ENDDATE="2079-06-06" ISACTUAL="1" ISACTIVE="1" /><APARTMENT ID="108547885" OBJECTID="165180617" OBJECTGUID="7e41a1ab-2b3a-4e4e-9a94-66c4105e5d1b" CHANGEID="600843529" NUMBER="4" APARTTYPE="2" OPERTYPEID="10" PREVID="0" NEXTID="0" UPDATEDATE="2024-09-10" STARTDATE="2024-09-10" ENDDATE="2079-06-06" ISACTUAL="1" ISACTIVE="1" /><APARTMENT ID="108547965" OBJECTID="165180785" OBJECTGUID="4c5bf5b4-92e8-4182-9506-14e3351d6cab" CHANGEID="600843914" NUMBER="1" APARTTYPE="2" OPERTYPEID="10" PREVID="0" NEXTID="0" UPDATEDATE="2024-09-10" STARTDATE="2024-09-10" ENDDATE="2079-06-06" ISACTUAL="1" ISACTIVE="1" /><APARTMENT ID="108547983" OBJECTID="165180807" OBJECTGUID="9dd21ab4-0a6b-4223-af16-cf3e1b58399c" CHANGEID="600843997" NUMBER="2" APARTTYPE="2" OPERTYPEID="10" PREVID="0" NEXTID="0" UPDATEDATE="2024-09-10" STARTDATE="2024-09-10" ENDDATE="2079-06-06" ISACTUAL="1" ISACTIVE="1" /><APARTMENT ID="108548110" OBJECTID="165181185" OBJECTGUID="a24892d8-977c-41c4-bbb4-1a997df6a293" CHANGEID="600844780" NUMBER="1" APARTTYPE="2" OPERTYPEID="10" PREVID="0" NEXTID="0" UPDATEDATE="2024-09-10" STARTDATE="2024-09-10" ENDDATE="2079-06-06" ISACTUAL="1" ISACTIVE="1" /><APARTMENT ID="108548131" OBJECTID="165181229" OBJECTGUID="9348df35-55d6-43a2-bdff-abccdc859acd" CHANGEID="600844890" NUMBER="1" APARTTYPE="2" OPERTYPEID="10" PREVID="0" NEXTID="0" UPDATEDATE="2024-09-10" STARTDATE="2024-09-10" ENDDATE="2079-06-06" ISACTUAL="1" ISACTIVE="1" /><APARTMENT ID="108557527" OBJECTID="165207588" OBJECTGUID="a2b16945-3f1c-4eaa-a473-db09acd9fb98" CHANGEID="600907684" NUMBER="1" APARTTYPE="1" OPERTYPEID="10" PREVID="0" NEXTID="0" UPDATEDATE="2024-09-11" STARTDATE="2024-09-11" ENDDATE="2079-06-06" ISACTUAL="1" ISACTIVE="1" /><APARTMENT ID="108557536" OBJECTID="165207691" OBJECTGUID="757d1404-64a7-424f-8cc9-bc81e26e1fe3" CHANGEID="600907795" NUMBER="1" APARTTYPE="1" OPERTYPEID="10" PREVID="0" NEXTID="0" UPDATEDATE="2024-09-11" STARTDATE="2024-09-11" ENDDATE="2079-06-06" ISACTUAL="1" ISACTIVE="1" /><APARTMENT ID="108566070" OBJECTID="165231426" OBJECTGUID="1e0eada4-0e55-4bd1-b3f0-e1f0a0776f56" CHANGEID="600946784" NUMBER="1" APARTTYPE="2" OPERTYPEID="10" PREVID="0" NEXTID="0" UPDATEDATE="2024-09-12" STARTDATE="2024-09-12" ENDDATE="2079-06-06" ISACTUAL="1" ISACTIVE="1" /><APARTMENT ID="108566071" OBJECTID="165231427" OBJECTGUID="30c6943b-c564-481d-ab24-c1f151e6a823" CHANGEID="600946785" NUMBER="2" APARTTYPE="2" OPERTYPEID="10" PREVID="0" NEXTID="0" UPDATEDATE="2024-09-12" STARTDATE="2024-09-12" ENDDATE="2079-06-06" ISACTUAL="1" ISACTIVE="1" /><APARTMENT ID="108567447" OBJECTID="165236548" OBJECTGUID="92d91adb-abea-4472-ac8e-58437372f53c" CHANGEID="600953831" NUMBER="1" APARTTYPE="2" OPERTYPEID="10" PREVID="0" NEXTID="0" UPDATEDATE="2024-09-12" STARTDATE="2024-09-12" ENDDATE="2079-06-06" ISACTUAL="1" ISACTIVE="1" /></APARTMENTS>